Workbook
Name lstCartoes: tbCartoes[Cartão]
Name lstCategorias: tbCategorias[Categoria]
Name lstGrupos: Categorias!$I$7:$I$10
Name lstMeses: Resumo!$B$7:$B$18
Name lstPagamento: Categorias!$J$7:$J$11
Name lstTipos: Categorias!$H$7:$H$9
Name lstTiposPatrimonio: Patrimônio!$P$6:$P$10

Sheet Painel
B2: Organização financeira | J2: PATRIMÔNIO LÍQUIDO | M2: MÊS DO PAINEL
B3: =IF(SUMPRODUCT((SUMIFS(tbLancamentos[Valor],tbLancamentos[Mês],$M$3,tbLancamentos[Descrição],tbContas[Conta])=0)*(DATE(YEAR($M$3),MONTH($M$3),tbContas[Dia do vencimento])<TODAY()))+$O$86+SUMPRODUCT((tbParcelas[1ª fatura]<=$M$3)*(tbParcelas[Última fatura]>=$M$3)*(COUNTIFS(tbLancamentos[Mês],$M$3,tbLancamentos[Descrição],tbParcelas[Descrição])=0))+($K$7<0)=0,"✓ Tudo em dia neste mês","⚠ "&IF(SUMPRODUCT((SUMIFS(tbLancamentos[Valor],tbLancamentos[Mês],$M$3,tbLancamentos[Descrição],tbContas[Conta])=0)*(DATE(YEAR($M$3),MONTH($M$3),tbContas[Dia do vencimento])<TODAY()))>0,SUMPRODUCT((SUMIFS(tbLancamentos[Valor],tbLancamentos[Mês],$M$3,tbLancamentos[Descrição],tbContas[Conta])=0)*(DATE(YEAR($M$3),MONTH($M$3),tbContas[Dia do vencimento])<TODAY()))&" conta(s) vencida(s) ","")&IF($O$86>0,$O$86&" categoria(s) acima do orçamento ","")&IF(SUMPRODUCT((tbParcelas[1ª fatura]<=$M$3)*(tbParcelas[Última fatura]>=$M$3)*(COUNTIFS(tbLancamentos[Mês],$M$3,tbLancamentos[Descrição],tbParcelas[Descrição])=0))>0,SUMPRODUCT((tbParcelas[1ª fatura]<=$M$3)*(tbParcelas[Última fatura]>=$M$3)*(COUNTIFS(tbLancamentos[Mês],$M$3,tbLancamentos[Descrição],tbParcelas[Descrição])=0))&" parcela(s) do cartão para lançar ","")&IF($K$7<0,"saldo do mês negativo","")) -> ⚠ 1 conta(s) vencida(s) 2 categoria(s) acima do orçamento 4 parcela(s) do cartão para lançar | J3: =SUM(tbPatrimonio[Valor atual])-SUM(tbDividas[Saldo devedor]) -> 5312.6995 | M3: 46296
B6: ● RECEITAS | E6: ● DESPESAS | H6: ● INVESTIDO | K6: ● SALDO DO MÊS | N6: ● TAXA DE POUPANÇA
B7: =SUMIFS(tbLancamentos[Valor],tbLancamentos[Mês],$M$3,tbLancamentos[Tipo],"Receita") -> 5800 | E7: =SUMIFS(tbLancamentos[Valor],tbLancamentos[Mês],$M$3,tbLancamentos[Tipo],"Despesa") -> 4095 | H7: =SUMIFS(tbLancamentos[Valor],tbLancamentos[Mês],$M$3,tbLancamentos[Tipo],"Investimento") -> 851.49 | K7: =B7-E7-H7 -> 853.51 | N7: =IF(B7=0,0,(B7-E7)/B7) -> 0.29396552
B8: =IFERROR(B7/SUMIFS(tbLancamentos[Valor],tbLancamentos[Mês],EDATE($M$3,-1),tbLancamentos[Tipo],"Receita")-1,"") -> 0 | E8: =IFERROR(E7/SUMIFS(tbLancamentos[Valor],tbLancamentos[Mês],EDATE($M$3,-1),tbLancamentos[Tipo],"Despesa")-1,"") -> 0.094261474 | H8: =IFERROR(H7/SUMIFS(tbLancamentos[Valor],tbLancamentos[Mês],EDATE($M$3,-1),tbLancamentos[Tipo],"Investimento")-1,"") -> -0.16277629 | K8: =K7-(SUMIFS(tbLancamentos[Valor],tbLancamentos[Mês],EDATE($M$3,-1),tbLancamentos[Tipo],"Receita")-SUMIFS(tbLancamentos[Valor],tbLancamentos[Mês],EDATE($M$3,-1),tbLancamentos[Tipo],"Despesa")-SUMIFS(tbLancamentos[Valor],tbLancamentos[Mês],EDATE($M$3,-1),tbLancamentos[Tipo],"Investimento")) -> -187.2 | N8: =IF(B7=0,"",IF(N7>=0.2,"✓ acima da meta de 20%","meta: guardar 20% da renda")) -> ✓ acima da meta de 20%
B27: Orçado x gasto no mês
B28: Categoria | D28: Orçado | E28: Gasto | F28: Diferença | G28: % usado
B29: =IFERROR(INDEX(tbCategorias[Categoria],MATCH(ROWS(B$29:B29),tbCategorias[Ordem],0)),"") -> Moradia | D29: =IF($B29="","",N(INDEX(tbCategorias[Orçamento mensal],MATCH($B29,tbCategorias[Categoria],0)))) -> 1200 | E29: =IF($B29="","",SUMIFS(tbLancamentos[Valor],tbLancamentos[Mês],$M$3,tbLancamentos[Categoria],$B29)) -> 1200 | F29: =IF($B29="","",D29-E29) -> 0 | G29: =IF(OR($B29="",N(D29)=0),"",E29/D29) -> 1
B30: =IFERROR(INDEX(tbCategorias[Categoria],MATCH(ROWS(B$29:B30),tbCategorias[Ordem],0)),"") -> Contas da casa | D30: =IF($B30="","",N(INDEX(tbCategorias[Orçamento mensal],MATCH($B30,tbCategorias[Categoria],0)))) -> 420 | E30: =IF($B30="","",SUMIFS(tbLancamentos[Valor],tbLancamentos[Mês],$M$3,tbLancamentos[Categoria],$B30)) -> 395.05 | F30: =IF($B30="","",D30-E30) -> 24.95 | G30: =IF(OR($B30="",N(D30)=0),"",E30/D30) -> 0.94059524
B31: =IFERROR(INDEX(tbCategorias[Categoria],MATCH(ROWS(B$29:B31),tbCategorias[Ordem],0)),"") -> Mercado | D31: =IF($B31="","",N(INDEX(tbCategorias[Orçamento mensal],MATCH($B31,tbCategorias[Categoria],0)))) -> 950 | E31: =IF($B31="","",SUMIFS(tbLancamentos[Valor],tbLancamentos[Mês],$M$3,tbLancamentos[Categoria],$B31)) -> 908.6 | F31: =IF($B31="","",D31-E31) -> 41.4 | G31: =IF(OR($B31="",N(D31)=0),"",E31/D31) -> 0.95642105
B32: =IFERROR(INDEX(tbCategorias[Categoria],MATCH(ROWS(B$29:B32),tbCategorias[Ordem],0)),"") -> Transporte | D32: =IF($B32="","",N(INDEX(tbCategorias[Orçamento mensal],MATCH($B32,tbCategorias[Categoria],0)))) -> 380 | E32: =IF($B32="","",SUMIFS(tbLancamentos[Valor],tbLancamentos[Mês],$M$3,tbLancamentos[Categoria],$B32)) -> 314.62 | F32: =IF($B32="","",D32-E32) -> 65.38 | G32: =IF(OR($B32="",N(D32)=0),"",E32/D32) -> 0.82794737
B33: =IFERROR(INDEX(tbCategorias[Categoria],MATCH(ROWS(B$29:B33),tbCategorias[Ordem],0)),"") -> Saúde | D33: =IF($B33="","",N(INDEX(tbCategorias[Orçamento mensal],MATCH($B33,tbCategorias[Categoria],0)))) -> 350 | E33: =IF($B33="","",SUMIFS(tbLancamentos[Valor],tbLancamentos[Mês],$M$3,tbLancamentos[Categoria],$B33)) -> 209.23 | F33: =IF($B33="","",D33-E33) -> 140.77 | G33: =IF(OR($B33="",N(D33)=0),"",E33/D33) -> 0.5978
B34: =IFERROR(INDEX(tbCategorias[Categoria],MATCH(ROWS(B$29:B34),tbCategorias[Ordem],0)),"") -> Educação | D34: =IF($B34="","",N(INDEX(tbCategorias[Orçamento mensal],MATCH($B34,tbCategorias[Categoria],0)))) -> 150 | E34: =IF($B34="","",SUMIFS(tbLancamentos[Valor],tbLancamentos[Mês],$M$3,tbLancamentos[Categoria],$B34)) -> 79.9 | F34: =IF($B34="","",D34-E34) -> 70.1 | G34: =IF(OR($B34="",N(D34)=0),"",E34/D34) -> 0.53266667
B35: =IFERROR(INDEX(tbCategorias[Categoria],MATCH(ROWS(B$29:B35),tbCategorias[Ordem],0)),"") -> Restaurantes e delivery | D35: =IF($B35="","",N(INDEX(tbCategorias[Orçamento mensal],MATCH($B35,tbCategorias[Categoria],0)))) -> 350 | E35: =IF($B35="","",SUMIFS(tbLancamentos[Valor],tbLancamentos[Mês],$M$3,tbLancamentos[Categoria],$B35)) -> 206.14 | F35: =IF($B35="","",D35-E35) -> 143.86 | G35: =IF(OR($B35="",N(D35)=0),"",E35/D35) -> 0.58897143
B36: =IFERROR(INDEX(tbCategorias[Categoria],MATCH(ROWS(B$29:B36),tbCategorias[Ordem],0)),"") -> Lazer | D36: =IF($B36="","",N(INDEX(tbCategorias[Orçamento mensal],MATCH($B36,tbCategorias[Categoria],0)))) -> 250 | E36: =IF($B36="","",SUMIFS(tbLancamentos[Valor],tbLancamentos[Mês],$M$3,tbLancamentos[Categoria],$B36)) -> 178.11 | F36: =IF($B36="","",D36-E36) -> 71.89 | G36: =IF(OR($B36="",N(D36)=0),"",E36/D36) -> 0.71244
B37: =IFERROR(INDEX(tbCategorias[Categoria],MATCH(ROWS(B$29:B37),tbCategorias[Ordem],0)),"") -> Assinaturas | D37: =IF($B37="","",N(INDEX(tbCategorias[Orçamento mensal],MATCH($B37,tbCategorias[Categoria],0)))) -> 90 | E37: =IF($B37="","",SUMIFS(tbLancamentos[Valor],tbLancamentos[Mês],$M$3,tbLancamentos[Categoria],$B37)) -> 66.8 | F37: =IF($B37="","",D37-E37) -> 23.2 | G37: =IF(OR($B37="",N(D37)=0),"",E37/D37) -> 0.74222222
B38: =IFERROR(INDEX(tbCategorias[Categoria],MATCH(ROWS(B$29:B38),tbCategorias[Ordem],0)),"") -> Compras | D38: =IF($B38="","",N(INDEX(tbCategorias[Orçamento mensal],MATCH($B38,tbCategorias[Categoria],0)))) -> 300 | E38: =IF($B38="","",SUMIFS(tbLancamentos[Valor],tbLancamentos[Mês],$M$3,tbLancamentos[Categoria],$B38)) -> 406.92 | F38: =IF($B38="","",D38-E38) -> -106.92 | G38: =IF(OR($B38="",N(D38)=0),"",E38/D38) -> 1.3564
B39: =IFERROR(INDEX(tbCategorias[Categoria],MATCH(ROWS(B$29:B39),tbCategorias[Ordem],0)),"") -> Outros | D39: =IF($B39="","",N(INDEX(tbCategorias[Orçamento mensal],MATCH($B39,tbCategorias[Categoria],0)))) -> 100 | E39: =IF($B39="","",SUMIFS(tbLancamentos[Valor],tbLancamentos[Mês],$M$3,tbLancamentos[Categoria],$B39)) -> 129.63 | F39: =IF($B39="","",D39-E39) -> -29.63 | G39: =IF(OR($B39="",N(D39)=0),"",E39/D39) -> 1.2963
B40: =IFERROR(INDEX(tbCategorias[Categoria],MATCH(ROWS(B$29:B40),tbCategorias[Ordem],0)),"") -> Investimentos | D40: =IF($B40="","",N(INDEX(tbCategorias[Orçamento mensal],MATCH($B40,tbCategorias[Categoria],0)))) -> 800 | E40: =IF($B40="","",SUMIFS(tbLancamentos[Valor],tbLancamentos[Mês],$M$3,tbLancamentos[Categoria],$B40)) -> 851.49 | F40: =IF($B40="","",D40-E40) -> -51.49 | G40: =IF(OR($B40="",N(D40)=0),"",E40/D40) -> 1.0643625
... B43: =IFERROR(INDEX(tbCategorias[Categoria],MATCH(ROWS(B$29:B43),tbCategorias[Ordem],0)),"") | D43: =IF($B43="","",N(INDEX(tbCategorias[Orçamento mensal],MATCH($B43,tbCategorias[Categoria],0)))) | E43: =IF($B43="","",SUMIFS(tbLancamentos[Valor],tbLancamentos[Mês],$M$3,tbLancamentos[Categoria],$B43)) | F43: =IF($B43="","",D43-E43) | G43: =IF(OR($B43="",N(D43)=0),"",E43/D43)
B44: Total | D44: =SUM(D29:D43) -> 5340 | E44: =SUM(E29:E43) -> 4946.49 | F44: =D44-E44 -> 393.51 | G44: =IF(D44=0,"",E44/D44) -> 0.92630899
B45: Em coral: passou do orçamento. Em Investimentos, aplicar mais que o planejado aparece em verde.
B64: Divisão da renda (regra 50/30/20) | J64: Metas
B65: Grupo | D65: Valor | E65: % da renda | F65: Referência | G65: Situação | J65: Meta | M65: Alvo | N65: Guardado | O65: Progresso
B66: Essencial | D66: =SUMIFS(tbLancamentos[Valor],tbLancamentos[Mês],$M$3,tbLancamentos[Grupo],$B66) -> 3107.4 | E66: =IF($B$7=0,"",D66/$B$7) -> 0.53575862 | F66: 0.5 | G66: =IF(E66="","",IF($B66="Investimento",IF(E66>=F66,"✓ dentro","abaixo da referência"),IF(E66<=F66,"✓ dentro","acima da referência"))) -> acima da referência | J66: =IFERROR(INDEX(tbMetas[Meta],ROWS(J$66:J66)),"") -> Reserva de emergência | M66: =IF($J66="","",INDEX(tbMetas[Valor alvo],ROWS(M$66:M66))) -> 18000 | N66: =IF($J66="","",INDEX(tbMetas[Já guardado],ROWS(N$66:N66))) -> 7200 | O66: =IF(OR($J66="",N(M66)=0),"",N66/M66) -> 0.4
B67: Estilo de vida | D67: =SUMIFS(tbLancamentos[Valor],tbLancamentos[Mês],$M$3,tbLancamentos[Grupo],$B67) -> 987.6 | E67: =IF($B$7=0,"",D67/$B$7) -> 0.17027586 | F67: 0.3 | G67: =IF(E67="","",IF($B67="Investimento",IF(E67>=F67,"✓ dentro","abaixo da referência"),IF(E67<=F67,"✓ dentro","acima da referência"))) -> ✓ dentro | J67: =IFERROR(INDEX(tbMetas[Meta],ROWS(J$66:J67)),"") -> Viagem de férias | M67: =IF($J67="","",INDEX(tbMetas[Valor alvo],ROWS(M$66:M67))) -> 5000 | N67: =IF($J67="","",INDEX(tbMetas[Já guardado],ROWS(N$66:N67))) -> 1800 | O67: =IF(OR($J67="",N(M67)=0),"",N67/M67) -> 0.36
B68: Investimento | D68: =SUMIFS(tbLancamentos[Valor],tbLancamentos[Mês],$M$3,tbLancamentos[Grupo],$B68) -> 851.49 | E68: =IF($B$7=0,"",D68/$B$7) -> 0.14680862 | F68: 0.2 | G68: =IF(E68="","",IF($B68="Investimento",IF(E68>=F68,"✓ dentro","abaixo da referência"),IF(E68<=F68,"✓ dentro","acima da referência"))) -> abaixo da referência | J68: =IFERROR(INDEX(tbMetas[Meta],ROWS(J$66:J68)),"") -> Notebook novo | M68: =IF($J68="","",INDEX(tbMetas[Valor alvo],ROWS(M$66:M68))) -> 4500 | N68: =IF($J68="","",INDEX(tbMetas[Já guardado],ROWS(N$66:N68))) -> 1200 | O68: =IF(OR($J68="",N(M68)=0),"",N68/M68) -> 0.26666667
B69: Sobrou no mês | D69: =K7 -> 853.51 | E69: =IF($B$7=0,"",D69/$B$7) -> 0.1471569 | J69: =IFERROR(INDEX(tbMetas[Meta],ROWS(J$66:J69)),"") -> Entrada do apartamento | M69: =IF($J69="","",INDEX(tbMetas[Valor alvo],ROWS(M$66:M69))) -> 40000 | N69: =IF($J69="","",INDEX(tbMetas[Já guardado],ROWS(N$66:N69))) -> 3000 | O69: =IF(OR($J69="",N(M69)=0),"",N69/M69) -> 0.075
J70: =IFERROR(INDEX(tbMetas[Meta],ROWS(J$66:J70)),"") | M70: =IF($J70="","",INDEX(tbMetas[Valor alvo],ROWS(M$66:M70))) | N70: =IF($J70="","",INDEX(tbMetas[Já guardado],ROWS(N$66:N70))) | O70: =IF(OR($J70="",N(M70)=0),"",N70/M70)
B73: Visão do ano (de janeiro até o mês escolhido)
B74: ● RECEBIDO NO ANO | E74: ● GASTO NO ANO | H74: ● INVESTIDO NO ANO | K74: ● SALDO NO ANO | N74: ● RESERVA DE EMERGÊNCIA
B75: =SUMIFS(tbLancamentos[Valor],tbLancamentos[Tipo],"Receita",tbLancamentos[Mês],">="&DATE(YEAR($M$3),1,1),tbLancamentos[Mês],"<="&$M$3) -> 61156.69 | E75: =SUMIFS(tbLancamentos[Valor],tbLancamentos[Tipo],"Despesa",tbLancamentos[Mês],">="&DATE(YEAR($M$3),1,1),tbLancamentos[Mês],"<="&$M$3) -> 39958.02 | H75: =SUMIFS(tbLancamentos[Valor],tbLancamentos[Tipo],"Investimento",tbLancamentos[Mês],">="&DATE(YEAR($M$3),1,1),tbLancamentos[Mês],"<="&$M$3) -> 7254.68 | K75: =B75-E75-H75 -> 13943.99 | N75: =IFERROR(INDEX(tbMetas[Já guardado],MATCH("Reserva*",tbMetas[Meta],0))/(E75/MONTH($M$3)),"") -> 1.8018911
B76: =B75/MONTH($M$3) -> 6115.669 | E76: =E75/MONTH($M$3) -> 3995.802 | H76: =H75/MONTH($M$3) -> 725.468 | K76: =IF(B75=0,"",(B75-E75)/B75) -> 0.3466288 | N76: ="dos seus gastos cobertos (ideal: 6)" -> dos seus gastos cobertos (ideal: 6)
B79: Maiores gastos do mês | J79: Ritmo do mês
B80: Data | C80: Descrição | F80: Categoria | H80: Valor | J80: Se o ritmo de gastos continuar igual até o fim do mês:
B81: =IF(Calc!$I3="","",INDEX(tbLancamentos[Data],Calc!$I3)) -> 46305 | C81: =IF(Calc!$I3="","",INDEX(tbLancamentos[Descrição],Calc!$I3)) -> Aluguel | F81: =IF(Calc!$I3="","",INDEX(tbLancamentos[Categoria],Calc!$I3)) -> Moradia | H81: =IF(Calc!$I3="","",INDEX(tbLancamentos[Valor],Calc!$I3)) -> 1200 | J81: Dias do mês considerados | O81: =IF(AND(YEAR(TODAY())=YEAR($M$3),MONTH(TODAY())=MONTH($M$3)),DAY(TODAY()),DAY(EOMONTH($M$3,0))) -> 26
B82: =IF(Calc!$I4="","",INDEX(tbLancamentos[Data],Calc!$I4)) -> 46308 | C82: =IF(Calc!$I4="","",INDEX(tbLancamentos[Descrição],Calc!$I4)) -> Livros | F82: =IF(Calc!$I4="","",INDEX(tbLancamentos[Categoria],Calc!$I4)) -> Compras | H82: =IF(Calc!$I4="","",INDEX(tbLancamentos[Valor],Calc!$I4)) -> 406.92 | J82: Gasto médio por dia | O82: =IF(N(O81)=0,0,E7/O81) -> 157.5
B83: =IF(Calc!$I5="","",INDEX(tbLancamentos[Data],Calc!$I5)) -> 46299 | C83: =IF(Calc!$I5="","",INDEX(tbLancamentos[Descrição],Calc!$I5)) -> Supermercado | F83: =IF(Calc!$I5="","",INDEX(tbLancamentos[Categoria],Calc!$I5)) -> Mercado | H83: =IF(Calc!$I5="","",INDEX(tbLancamentos[Valor],Calc!$I5)) -> 318.36 | J83: Projeção de gasto no mês | O83: =O82*DAY(EOMONTH($M$3,0)) -> 4882.5
B84: =IF(Calc!$I6="","",INDEX(tbLancamentos[Data],Calc!$I6)) -> 46306 | C84: =IF(Calc!$I6="","",INDEX(tbLancamentos[Descrição],Calc!$I6)) -> Supermercado | F84: =IF(Calc!$I6="","",INDEX(tbLancamentos[Categoria],Calc!$I6)) -> Mercado | H84: =IF(Calc!$I6="","",INDEX(tbLancamentos[Valor],Calc!$I6)) -> 308.9 | J84: Orçamento de despesas | O84: =SUMIFS(tbCategorias[Orçamento mensal],tbCategorias[Tipo],"Despesa") -> 4540
B85: =IF(Calc!$I7="","",INDEX(tbLancamentos[Data],Calc!$I7)) -> 46307 | C85: =IF(Calc!$I7="","",INDEX(tbLancamentos[Descrição],Calc!$I7)) -> Conta de luz | F85: =IF(Calc!$I7="","",INDEX(tbLancamentos[Categoria],Calc!$I7)) -> Contas da casa | H85: =IF(Calc!$I7="","",INDEX(tbLancamentos[Valor],Calc!$I7)) -> 165.63 | J85: Projeção x orçamento | O85: =IF(N(O84)=0,"",O83/O84) -> 1.0754405
B86: =IF(Calc!$I8="","",INDEX(tbLancamentos[Data],Calc!$I8)) -> 46312 | C86: =IF(Calc!$I8="","",INDEX(tbLancamentos[Descrição],Calc!$I8)) -> Padaria | F86: =IF(Calc!$I8="","",INDEX(tbLancamentos[Categoria],Calc!$I8)) -> Mercado | H86: =IF(Calc!$I8="","",INDEX(tbLancamentos[Valor],Calc!$I8)) -> 160.93 | J86: Categorias acima do orçamento | O86: =COUNTIFS(G29:G43,">1",B29:B43,"<>Investimentos") -> 2
B87: =IF(Calc!$I9="","",INDEX(tbLancamentos[Data],Calc!$I9)) -> 46314 | C87: =IF(Calc!$I9="","",INDEX(tbLancamentos[Descrição],Calc!$I9)) -> Combustível | F87: =IF(Calc!$I9="","",INDEX(tbLancamentos[Categoria],Calc!$I9)) -> Transporte | H87: =IF(Calc!$I9="","",INDEX(tbLancamentos[Valor],Calc!$I9)) -> 153.36 | J87: Contas fixas ainda não pagas | O87: =SUMPRODUCT(tbContas[Valor previsto]*(SUMIFS(tbLancamentos[Valor],tbLancamentos[Mês],$M$3,tbLancamentos[Descrição],tbContas[Conta])=0)) -> 75
B90: Mapa de calor: gasto por categoria em cada mês
B91: Categoria | D91: =INDEX(Resumo!$B$7:$B$18,COLUMNS($D91:D91)) -> 46023 | E91: =INDEX(Resumo!$B$7:$B$18,COLUMNS($D91:E91)) -> 46054 | F91: =INDEX(Resumo!$B$7:$B$18,COLUMNS($D91:F91)) -> 46082 | G91: =INDEX(Resumo!$B$7:$B$18,COLUMNS($D91:G91)) -> 46113 | H91: =INDEX(Resumo!$B$7:$B$18,COLUMNS($D91:H91)) -> 46143 | I91: =INDEX(Resumo!$B$7:$B$18,COLUMNS($D91:I91)) -> 46174 | J91: =INDEX(Resumo!$B$7:$B$18,COLUMNS($D91:J91)) -> 46204 | K91: =INDEX(Resumo!$B$7:$B$18,COLUMNS($D91:K91)) -> 46235 | ... O91: =INDEX(Resumo!$B$7:$B$18,COLUMNS($D91:O91)) -> 46357 | P91: Total
B92: =B29 -> Moradia | D92: =IF($B92="","",SUMIFS(tbLancamentos[Valor],tbLancamentos[Categoria],$B92,tbLancamentos[Mês],D$91)) -> 1200 | E92: =IF($B92="","",SUMIFS(tbLancamentos[Valor],tbLancamentos[Categoria],$B92,tbLancamentos[Mês],E$91)) -> 1200 | F92: =IF($B92="","",SUMIFS(tbLancamentos[Valor],tbLancamentos[Categoria],$B92,tbLancamentos[Mês],F$91)) -> 1200 | G92: =IF($B92="","",SUMIFS(tbLancamentos[Valor],tbLancamentos[Categoria],$B92,tbLancamentos[Mês],G$91)) -> 1200 | H92: =IF($B92="","",SUMIFS(tbLancamentos[Valor],tbLancamentos[Categoria],$B92,tbLancamentos[Mês],H$91)) -> 1200 | I92: =IF($B92="","",SUMIFS(tbLancamentos[Valor],tbLancamentos[Categoria],$B92,tbLancamentos[Mês],I$91)) -> 1200 | J92: =IF($B92="","",SUMIFS(tbLancamentos[Valor],tbLancamentos[Categoria],$B92,tbLancamentos[Mês],J$91)) -> 1200 | K92: =IF($B92="","",SUMIFS(tbLancamentos[Valor],tbLancamentos[Categoria],$B92,tbLancamentos[Mês],K$91)) -> 1200 | ... O92: =IF($B92="","",SUMIFS(tbLancamentos[Valor],tbLancamentos[Categoria],$B92,tbLancamentos[Mês],O$91)) -> 0 | P92: =IF($B92="","",SUM(D92:O92)) -> 12000
B93: =B30 -> Contas da casa | D93: =IF($B93="","",SUMIFS(tbLancamentos[Valor],tbLancamentos[Categoria],$B93,tbLancamentos[Mês],D$91)) -> 392.79 | E93: =IF($B93="","",SUMIFS(tbLancamentos[Valor],tbLancamentos[Categoria],$B93,tbLancamentos[Mês],E$91)) -> 369.93 | F93: =IF($B93="","",SUMIFS(tbLancamentos[Valor],tbLancamentos[Categoria],$B93,tbLancamentos[Mês],F$91)) -> 427.65 | G93: =IF($B93="","",SUMIFS(tbLancamentos[Valor],tbLancamentos[Categoria],$B93,tbLancamentos[Mês],G$91)) -> 394.54 | H93: =IF($B93="","",SUMIFS(tbLancamentos[Valor],tbLancamentos[Categoria],$B93,tbLancamentos[Mês],H$91)) -> 442.77 | I93: =IF($B93="","",SUMIFS(tbLancamentos[Valor],tbLancamentos[Categoria],$B93,tbLancamentos[Mês],I$91)) -> 424.36 | J93: =IF($B93="","",SUMIFS(tbLancamentos[Valor],tbLancamentos[Categoria],$B93,tbLancamentos[Mês],J$91)) -> 402.65 | K93: =IF($B93="","",SUMIFS(tbLancamentos[Valor],tbLancamentos[Categoria],$B93,tbLancamentos[Mês],K$91)) -> 430.62 | ... O93: =IF($B93="","",SUMIFS(tbLancamentos[Valor],tbLancamentos[Categoria],$B93,tbLancamentos[Mês],O$91)) -> 0 | P93: =IF($B93="","",SUM(D93:O93)) -> 4092.88
B94: =B31 -> Mercado | D94: =IF($B94="","",SUMIFS(tbLancamentos[Valor],tbLancamentos[Categoria],$B94,tbLancamentos[Mês],D$91)) -> 719.18 | E94: =IF($B94="","",SUMIFS(tbLancamentos[Valor],tbLancamentos[Categoria],$B94,tbLancamentos[Mês],E$91)) -> 887.21 | F94: =IF($B94="","",SUMIFS(tbLancamentos[Valor],tbLancamentos[Categoria],$B94,tbLancamentos[Mês],F$91)) -> 791.68 | G94: =IF($B94="","",SUMIFS(tbLancamentos[Valor],tbLancamentos[Categoria],$B94,tbLancamentos[Mês],G$91)) -> 987.88 | H94: =IF($B94="","",SUMIFS(tbLancamentos[Valor],tbLancamentos[Categoria],$B94,tbLancamentos[Mês],H$91)) -> 924.97 | I94: =IF($B94="","",SUMIFS(tbLancamentos[Valor],tbLancamentos[Categoria],$B94,tbLancamentos[Mês],I$91)) -> 1126.54 | J94: =IF($B94="","",SUMIFS(tbLancamentos[Valor],tbLancamentos[Categoria],$B94,tbLancamentos[Mês],J$91)) -> 957.68 | K94: =IF($B94="","",SUMIFS(tbLancamentos[Valor],tbLancamentos[Categoria],$B94,tbLancamentos[Mês],K$91)) -> 952.2 | ... O94: =IF($B94="","",SUMIFS(tbLancamentos[Valor],tbLancamentos[Categoria],$B94,tbLancamentos[Mês],O$91)) -> 0 | P94: =IF($B94="","",SUM(D94:O94)) -> 8968.39
B95: =B32 -> Transporte | D95: =IF($B95="","",SUMIFS(tbLancamentos[Valor],tbLancamentos[Categoria],$B95,tbLancamentos[Mês],D$91)) -> 322.88 | E95: =IF($B95="","",SUMIFS(tbLancamentos[Valor],tbLancamentos[Categoria],$B95,tbLancamentos[Mês],E$91)) -> 269.38 | F95: =IF($B95="","",SUMIFS(tbLancamentos[Valor],tbLancamentos[Categoria],$B95,tbLancamentos[Mês],F$91)) -> 369.33 | G95: =IF($B95="","",SUMIFS(tbLancamentos[Valor],tbLancamentos[Categoria],$B95,tbLancamentos[Mês],G$91)) -> 314.51 | H95: =IF($B95="","",SUMIFS(tbLancamentos[Valor],tbLancamentos[Categoria],$B95,tbLancamentos[Mês],H$91)) -> 341.78 | I95: =IF($B95="","",SUMIFS(tbLancamentos[Valor],tbLancamentos[Categoria],$B95,tbLancamentos[Mês],I$91)) -> 277.92 | J95: =IF($B95="","",SUMIFS(tbLancamentos[Valor],tbLancamentos[Categoria],$B95,tbLancamentos[Mês],J$91)) -> 341.75 | K95: =IF($B95="","",SUMIFS(tbLancamentos[Valor],tbLancamentos[Categoria],$B95,tbLancamentos[Mês],K$91)) -> 303.57 | ... O95: =IF($B95="","",SUMIFS(tbLancamentos[Valor],tbLancamentos[Categoria],$B95,tbLancamentos[Mês],O$91)) -> 0 | P95: =IF($B95="","",SUM(D95:O95)) -> 3140.38
B96: =B33 -> Saúde | D96: =IF($B96="","",SUMIFS(tbLancamentos[Valor],tbLancamentos[Categoria],$B96,tbLancamentos[Mês],D$91)) -> 159.8 | E96: =IF($B96="","",SUMIFS(tbLancamentos[Valor],tbLancamentos[Categoria],$B96,tbLancamentos[Mês],E$91)) -> 252.27 | F96: =IF($B96="","",SUMIFS(tbLancamentos[Valor],tbLancamentos[Categoria],$B96,tbLancamentos[Mês],F$91)) -> 266.74 | G96: =IF($B96="","",SUMIFS(tbLancamentos[Valor],tbLancamentos[Categoria],$B96,tbLancamentos[Mês],G$91)) -> 159.8 | H96: =IF($B96="","",SUMIFS(tbLancamentos[Valor],tbLancamentos[Categoria],$B96,tbLancamentos[Mês],H$91)) -> 159.8 | I96: =IF($B96="","",SUMIFS(tbLancamentos[Valor],tbLancamentos[Categoria],$B96,tbLancamentos[Mês],I$91)) -> 159.8 | J96: =IF($B96="","",SUMIFS(tbLancamentos[Valor],tbLancamentos[Categoria],$B96,tbLancamentos[Mês],J$91)) -> 159.8 | K96: =IF($B96="","",SUMIFS(tbLancamentos[Valor],tbLancamentos[Categoria],$B96,tbLancamentos[Mês],K$91)) -> 159.8 | ... O96: =IF($B96="","",SUMIFS(tbLancamentos[Valor],tbLancamentos[Categoria],$B96,tbLancamentos[Mês],O$91)) -> 0 | P96: =IF($B96="","",SUM(D96:O96)) -> 1891.69
B97: =B34 -> Educação | D97: =IF($B97="","",SUMIFS(tbLancamentos[Valor],tbLancamentos[Categoria],$B97,tbLancamentos[Mês],D$91)) -> 79.9 | E97: =IF($B97="","",SUMIFS(tbLancamentos[Valor],tbLancamentos[Categoria],$B97,tbLancamentos[Mês],E$91)) -> 79.9 | F97: =IF($B97="","",SUMIFS(tbLancamentos[Valor],tbLancamentos[Categoria],$B97,tbLancamentos[Mês],F$91)) -> 79.9 | G97: =IF($B97="","",SUMIFS(tbLancamentos[Valor],tbLancamentos[Categoria],$B97,tbLancamentos[Mês],G$91)) -> 79.9 | H97: =IF($B97="","",SUMIFS(tbLancamentos[Valor],tbLancamentos[Categoria],$B97,tbLancamentos[Mês],H$91)) -> 79.9 | I97: =IF($B97="","",SUMIFS(tbLancamentos[Valor],tbLancamentos[Categoria],$B97,tbLancamentos[Mês],I$91)) -> 79.9 | J97: =IF($B97="","",SUMIFS(tbLancamentos[Valor],tbLancamentos[Categoria],$B97,tbLancamentos[Mês],J$91)) -> 79.9 | K97: =IF($B97="","",SUMIFS(tbLancamentos[Valor],tbLancamentos[Categoria],$B97,tbLancamentos[Mês],K$91)) -> 79.9 | ... O97: =IF($B97="","",SUMIFS(tbLancamentos[Valor],tbLancamentos[Categoria],$B97,tbLancamentos[Mês],O$91)) -> 0 | P97: =IF($B97="","",SUM(D97:O97)) -> 799
B98: =B35 -> Restaurantes e delivery | D98: =IF($B98="","",SUMIFS(tbLancamentos[Valor],tbLancamentos[Categoria],$B98,tbLancamentos[Mês],D$91)) -> 278.23 | E98: =IF($B98="","",SUMIFS(tbLancamentos[Valor],tbLancamentos[Categoria],$B98,tbLancamentos[Mês],E$91)) -> 333.88 | F98: =IF($B98="","",SUMIFS(tbLancamentos[Valor],tbLancamentos[Categoria],$B98,tbLancamentos[Mês],F$91)) -> 327.96 | G98: =IF($B98="","",SUMIFS(tbLancamentos[Valor],tbLancamentos[Categoria],$B98,tbLancamentos[Mês],G$91)) -> 247.15 | H98: =IF($B98="","",SUMIFS(tbLancamentos[Valor],tbLancamentos[Categoria],$B98,tbLancamentos[Mês],H$91)) -> 244.17 | I98: =IF($B98="","",SUMIFS(tbLancamentos[Valor],tbLancamentos[Categoria],$B98,tbLancamentos[Mês],I$91)) -> 341.56 | J98: =IF($B98="","",SUMIFS(tbLancamentos[Valor],tbLancamentos[Categoria],$B98,tbLancamentos[Mês],J$91)) -> 403.46 | K98: =IF($B98="","",SUMIFS(tbLancamentos[Valor],tbLancamentos[Categoria],$B98,tbLancamentos[Mês],K$91)) -> 274.64 | ... O98: =IF($B98="","",SUMIFS(tbLancamentos[Valor],tbLancamentos[Categoria],$B98,tbLancamentos[Mês],O$91)) -> 0 | P98: =IF($B98="","",SUM(D98:O98)) -> 2970.11
B99: =B36 -> Lazer | D99: =IF($B99="","",SUMIFS(tbLancamentos[Valor],tbLancamentos[Categoria],$B99,tbLancamentos[Mês],D$91)) -> 135.1 | E99: =IF($B99="","",SUMIFS(tbLancamentos[Valor],tbLancamentos[Categoria],$B99,tbLancamentos[Mês],E$91)) -> 312.67 | F99: =IF($B99="","",SUMIFS(tbLancamentos[Valor],tbLancamentos[Categoria],$B99,tbLancamentos[Mês],F$91)) -> 297.66 | G99: =IF($B99="","",SUMIFS(tbLancamentos[Valor],tbLancamentos[Categoria],$B99,tbLancamentos[Mês],G$91)) -> 172.24 | H99: =IF($B99="","",SUMIFS(tbLancamentos[Valor],tbLancamentos[Categoria],$B99,tbLancamentos[Mês],H$91)) -> 234.03 | I99: =IF($B99="","",SUMIFS(tbLancamentos[Valor],tbLancamentos[Categoria],$B99,tbLancamentos[Mês],I$91)) -> 277.37 | J99: =IF($B99="","",SUMIFS(tbLancamentos[Valor],tbLancamentos[Categoria],$B99,tbLancamentos[Mês],J$91)) -> 142.92 | K99: =IF($B99="","",SUMIFS(tbLancamentos[Valor],tbLancamentos[Categoria],$B99,tbLancamentos[Mês],K$91)) -> 225.35 | ... O99: =IF($B99="","",SUMIFS(tbLancamentos[Valor],tbLancamentos[Categoria],$B99,tbLancamentos[Mês],O$91)) -> 0 | P99: =IF($B99="","",SUM(D99:O99)) -> 2218.48
B100: =B37 -> Assinaturas | D100: =IF($B100="","",SUMIFS(tbLancamentos[Valor],tbLancamentos[Categoria],$B100,tbLancamentos[Mês],D$91)) -> 66.8 | E100: =IF($B100="","",SUMIFS(tbLancamentos[Valor],tbLancamentos[Categoria],$B100,tbLancamentos[Mês],E$91)) -> 66.8 | F100: =IF($B100="","",SUMIFS(tbLancamentos[Valor],tbLancamentos[Categoria],$B100,tbLancamentos[Mês],F$91)) -> 66.8 | G100: =IF($B100="","",SUMIFS(tbLancamentos[Valor],tbLancamentos[Categoria],$B100,tbLancamentos[Mês],G$91)) -> 66.8 | H100: =IF($B100="","",SUMIFS(tbLancamentos[Valor],tbLancamentos[Categoria],$B100,tbLancamentos[Mês],H$91)) -> 66.8 | I100: =IF($B100="","",SUMIFS(tbLancamentos[Valor],tbLancamentos[Categoria],$B100,tbLancamentos[Mês],I$91)) -> 66.8 | J100: =IF($B100="","",SUMIFS(tbLancamentos[Valor],tbLancamentos[Categoria],$B100,tbLancamentos[Mês],J$91)) -> 66.8 | K100: =IF($B100="","",SUMIFS(tbLancamentos[Valor],tbLancamentos[Categoria],$B100,tbLancamentos[Mês],K$91)) -> 66.8 | ... O100: =IF($B100="","",SUMIFS(tbLancamentos[Valor],tbLancamentos[Categoria],$B100,tbLancamentos[Mês],O$91)) -> 0 | P100: =IF($B100="","",SUM(D100:O100)) -> 668
B101: =B38 -> Compras | D101: =IF($B101="","",SUMIFS(tbLancamentos[Valor],tbLancamentos[Categoria],$B101,tbLancamentos[Mês],D$91)) -> 211.33 | E101: =IF($B101="","",SUMIFS(tbLancamentos[Valor],tbLancamentos[Categoria],$B101,tbLancamentos[Mês],E$91)) -> 69.77 | F101: =IF($B101="","",SUMIFS(tbLancamentos[Valor],tbLancamentos[Categoria],$B101,tbLancamentos[Mês],F$91)) -> 281.74 | G101: =IF($B101="","",SUMIFS(tbLancamentos[Valor],tbLancamentos[Categoria],$B101,tbLancamentos[Mês],G$91)) -> 314.12 | H101: =IF($B101="","",SUMIFS(tbLancamentos[Valor],tbLancamentos[Categoria],$B101,tbLancamentos[Mês],H$91)) -> 294.89 | I101: =IF($B101="","",SUMIFS(tbLancamentos[Valor],tbLancamentos[Categoria],$B101,tbLancamentos[Mês],I$91)) -> 295.19 | J101: =IF($B101="","",SUMIFS(tbLancamentos[Valor],tbLancamentos[Categoria],$B101,tbLancamentos[Mês],J$91)) -> 503.91 | K101: =IF($B101="","",SUMIFS(tbLancamentos[Valor],tbLancamentos[Categoria],$B101,tbLancamentos[Mês],K$91)) -> 260.78 | ... O101: =IF($B101="","",SUMIFS(tbLancamentos[Valor],tbLancamentos[Categoria],$B101,tbLancamentos[Mês],O$91)) -> 0 | P101: =IF($B101="","",SUM(D101:O101)) -> 2788.25
B102: =B39 -> Outros | D102: =IF($B102="","",SUMIFS(tbLancamentos[Valor],tbLancamentos[Categoria],$B102,tbLancamentos[Mês],D$91)) -> 0 | E102: =IF($B102="","",SUMIFS(tbLancamentos[Valor],tbLancamentos[Categoria],$B102,tbLancamentos[Mês],E$91)) -> 48.1 | F102: =IF($B102="","",SUMIFS(tbLancamentos[Valor],tbLancamentos[Categoria],$B102,tbLancamentos[Mês],F$91)) -> 0 | G102: =IF($B102="","",SUMIFS(tbLancamentos[Valor],tbLancamentos[Categoria],$B102,tbLancamentos[Mês],G$91)) -> 0 | H102: =IF($B102="","",SUMIFS(tbLancamentos[Valor],tbLancamentos[Categoria],$B102,tbLancamentos[Mês],H$91)) -> 0 | I102: =IF($B102="","",SUMIFS(tbLancamentos[Valor],tbLancamentos[Categoria],$B102,tbLancamentos[Mês],I$91)) -> 50.6 | J102: =IF($B102="","",SUMIFS(tbLancamentos[Valor],tbLancamentos[Categoria],$B102,tbLancamentos[Mês],J$91)) -> 0 | K102: =IF($B102="","",SUMIFS(tbLancamentos[Valor],tbLancamentos[Categoria],$B102,tbLancamentos[Mês],K$91)) -> 116.77 | ... O102: =IF($B102="","",SUMIFS(tbLancamentos[Valor],tbLancamentos[Categoria],$B102,tbLancamentos[Mês],O$91)) -> 0 | P102: =IF($B102="","",SUM(D102:O102)) -> 420.84
B103: =B40 -> Investimentos | D103: =IF($B103="","",SUMIFS(tbLancamentos[Valor],tbLancamentos[Categoria],$B103,tbLancamentos[Mês],D$91)) -> 600 | E103: =IF($B103="","",SUMIFS(tbLancamentos[Valor],tbLancamentos[Categoria],$B103,tbLancamentos[Mês],E$91)) -> 600 | F103: =IF($B103="","",SUMIFS(tbLancamentos[Valor],tbLancamentos[Categoria],$B103,tbLancamentos[Mês],F$91)) -> 600 | G103: =IF($B103="","",SUMIFS(tbLancamentos[Valor],tbLancamentos[Categoria],$B103,tbLancamentos[Mês],G$91)) -> 600 | H103: =IF($B103="","",SUMIFS(tbLancamentos[Valor],tbLancamentos[Categoria],$B103,tbLancamentos[Mês],H$91)) -> 926.39 | I103: =IF($B103="","",SUMIFS(tbLancamentos[Valor],tbLancamentos[Categoria],$B103,tbLancamentos[Mês],I$91)) -> 600 | J103: =IF($B103="","",SUMIFS(tbLancamentos[Valor],tbLancamentos[Categoria],$B103,tbLancamentos[Mês],J$91)) -> 859.76 | K103: =IF($B103="","",SUMIFS(tbLancamentos[Valor],tbLancamentos[Categoria],$B103,tbLancamentos[Mês],K$91)) -> 600 | ... O103: =IF($B103="","",SUMIFS(tbLancamentos[Valor],tbLancamentos[Categoria],$B103,tbLancamentos[Mês],O$91)) -> 0 | P103: =IF($B103="","",SUM(D103:O103)) -> 7254.68
... B106: =B43 | D106: =IF($B106="","",SUMIFS(tbLancamentos[Valor],tbLancamentos[Categoria],$B106,tbLancamentos[Mês],D$91)) | E106: =IF($B106="","",SUMIFS(tbLancamentos[Valor],tbLancamentos[Categoria],$B106,tbLancamentos[Mês],E$91)) | F106: =IF($B106="","",SUMIFS(tbLancamentos[Valor],tbLancamentos[Categoria],$B106,tbLancamentos[Mês],F$91)) | G106: =IF($B106="","",SUMIFS(tbLancamentos[Valor],tbLancamentos[Categoria],$B106,tbLancamentos[Mês],G$91)) | H106: =IF($B106="","",SUMIFS(tbLancamentos[Valor],tbLancamentos[Categoria],$B106,tbLancamentos[Mês],H$91)) | I106: =IF($B106="","",SUMIFS(tbLancamentos[Valor],tbLancamentos[Categoria],$B106,tbLancamentos[Mês],I$91)) | J106: =IF($B106="","",SUMIFS(tbLancamentos[Valor],tbLancamentos[Categoria],$B106,tbLancamentos[Mês],J$91)) | K106: =IF($B106="","",SUMIFS(tbLancamentos[Valor],tbLancamentos[Categoria],$B106,tbLancamentos[Mês],K$91)) | ... O106: =IF($B106="","",SUMIFS(tbLancamentos[Valor],tbLancamentos[Categoria],$B106,tbLancamentos[Mês],O$91)) | P106: =IF($B106="","",SUM(D106:O106))
B107: Total | D107: =SUM(D92:D106) -> 4166.01 | E107: =SUM(E92:E106) -> 4489.91 | F107: =SUM(F92:F106) -> 4709.46 | G107: =SUM(G92:G106) -> 4536.94 | H107: =SUM(H92:H106) -> 4915.5 | I107: =SUM(I92:I106) -> 4900.04 | J107: =SUM(J92:J106) -> 5118.63 | K107: =SUM(K92:K106) -> 4670.43 | ... P107: =SUM(P92:P106) -> 47212.7
B108: Cada linha tem a própria escala: a cor mais forte marca o mês em que aquela categoria pesou mais.
B110: Células douradas: você preenche. O resto é calculado. Os dados que vêm na planilha são de exemplo: veja a aba "Como usar".
B112: =HYPERLINK("https://ottavvi.github.io/site-portfolio/","Criado por Otávio · ottavvi.dev") -> Criado por Otávio · ottavvi.dev

Sheet Celular
B1: Minhas finanças
B2: =IF(SUMPRODUCT((SUMIFS(tbLancamentos[Valor],tbLancamentos[Mês],$C$6,tbLancamentos[Descrição],tbContas[Conta])=0)*(DATE(YEAR($C$6),MONTH($C$6),tbContas[Dia do vencimento])<TODAY()))+SUMPRODUCT((tbCategorias[Tipo]="Despesa")*(SUMIFS(tbLancamentos[Valor],tbLancamentos[Mês],$C$6,tbLancamentos[Categoria],tbCategorias[Categoria])>tbCategorias[Orçamento mensal]))+SUMPRODUCT((tbParcelas[1ª fatura]<=$C$6)*(tbParcelas[Última fatura]>=$C$6)*(COUNTIFS(tbLancamentos[Mês],$C$6,tbLancamentos[Descrição],tbParcelas[Descrição])=0))+($C$12<0)=0,"✓ Tudo em dia neste mês","⚠ "&IF(SUMPRODUCT((SUMIFS(tbLancamentos[Valor],tbLancamentos[Mês],$C$6,tbLancamentos[Descrição],tbContas[Conta])=0)*(DATE(YEAR($C$6),MONTH($C$6),tbContas[Dia do vencimento])<TODAY()))>0,SUMPRODUCT((SUMIFS(tbLancamentos[Valor],tbLancamentos[Mês],$C$6,tbLancamentos[Descrição],tbContas[Conta])=0)*(DATE(YEAR($C$6),MONTH($C$6),tbContas[Dia do vencimento])<TODAY()))&" conta(s) vencida(s) ","")&IF(SUMPRODUCT((tbCategorias[Tipo]="Despesa")*(SUMIFS(tbLancamentos[Valor],tbLancamentos[Mês],$C$6,tbLancamentos[Categoria],tbCategorias[Categoria])>tbCategorias[Orçamento mensal]))>0,SUMPRODUCT((tbCategorias[Tipo]="Despesa")*(SUMIFS(tbLancamentos[Valor],tbLancamentos[Mês],$C$6,tbLancamentos[Categoria],tbCategorias[Categoria])>tbCategorias[Orçamento mensal]))&" categoria(s) acima do orçamento ","")&IF(SUMPRODUCT((tbParcelas[1ª fatura]<=$C$6)*(tbParcelas[Última fatura]>=$C$6)*(COUNTIFS(tbLancamentos[Mês],$C$6,tbLancamentos[Descrição],tbParcelas[Descrição])=0))>0,SUMPRODUCT((tbParcelas[1ª fatura]<=$C$6)*(tbParcelas[Última fatura]>=$C$6)*(COUNTIFS(tbLancamentos[Mês],$C$6,tbLancamentos[Descrição],tbParcelas[Descrição])=0))&" parcela(s) do cartão para lançar ","")&IF($C$12<0,"saldo do mês negativo","")) -> ⚠ 1 conta(s) vencida(s) 2 categoria(s) acima do orçamento 4 parcela(s) do cartão para lançar
B3: =HYPERLINK("#'Painel'!A1","Painel completo ›") -> Painel completo › | C3: =HYPERLINK("#'Lançamentos'!A1","Lançar gasto ›") -> Lançar gasto ›
B4: =HYPERLINK("#'Contas fixas'!A1","Contas fixas ›") -> Contas fixas › | C4: =HYPERLINK("#'Metas'!A1","Metas ›") -> Metas ›
B6: Mês | C6: 46296
B8: Resumo do mês
B9: Receitas | C9: =SUMIFS(tbLancamentos[Valor],tbLancamentos[Mês],$C$6,tbLancamentos[Tipo],"Receita") -> 5800
B10: Despesas | C10: =SUMIFS(tbLancamentos[Valor],tbLancamentos[Mês],$C$6,tbLancamentos[Tipo],"Despesa") -> 4095
B11: Investido | C11: =SUMIFS(tbLancamentos[Valor],tbLancamentos[Mês],$C$6,tbLancamentos[Tipo],"Investimento") -> 851.49
B12: Saldo do mês | C12: =C9-C10-C11 -> 853.51
B13: Taxa de poupança | C13: =IF(C9=0,0,(C9-C10)/C9) -> 0.29396552
B14: Despesas vs mês anterior | C14: =IFERROR(C10/SUMIFS(tbLancamentos[Valor],tbLancamentos[Mês],EDATE($C$6,-1),tbLancamentos[Tipo],"Despesa")-1,"") -> 0.094261474
B16: Orçamento do mês
B17: Orçamento de despesas | C17: =SUMIFS(tbCategorias[Orçamento mensal],tbCategorias[Tipo],"Despesa") -> 4540
B18: % do orçamento usado | C18: =IF(C17=0,"",C10/C17) -> 0.90198238
B19: Projeção até o fim do mês | C19: =IF(AND(YEAR(TODAY())=YEAR($C$6),MONTH(TODAY())=MONTH($C$6)),C10/DAY(TODAY())*DAY(EOMONTH($C$6,0)),C10) -> 4882.5
B20: Projeção x orçamento | C20: =IF(C17=0,"",C19/C17) -> 1.0754405
B22: Onde mais gastou
B23: =Calc!N3 -> Moradia | C23: =IF(Calc!M3="","",ROUND(Calc!M3,2)) -> 1200
B24: =Calc!N4 -> Mercado | C24: =IF(Calc!M4="","",ROUND(Calc!M4,2)) -> 908.6
B25: =Calc!N5 -> Compras | C25: =IF(Calc!M5="","",ROUND(Calc!M5,2)) -> 406.92
B26: =Calc!N6 -> Contas da casa | C26: =IF(Calc!M6="","",ROUND(Calc!M6,2)) -> 395.05
B27: =Calc!N7 -> Transporte | C27: =IF(Calc!M7="","",ROUND(Calc!M7,2)) -> 314.62
B29: Contas fixas
B30: Contas pagas | C30: =SUMPRODUCT(--(SUMIFS(tbLancamentos[Valor],tbLancamentos[Mês],$C$6,tbLancamentos[Descrição],tbContas[Conta])>0))&" de "&ROWS(tbContas[]) -> 10 de 12
B31: Falta pagar | C31: =SUMPRODUCT(tbContas[Valor previsto]*(SUMIFS(tbLancamentos[Valor],tbLancamentos[Mês],$C$6,tbLancamentos[Descrição],tbContas[Conta])=0)) -> 75
B32: Contas vencidas | C32: =SUMPRODUCT((SUMIFS(tbLancamentos[Valor],tbLancamentos[Mês],$C$6,tbLancamentos[Descrição],tbContas[Conta])=0)*(DATE(YEAR($C$6),MONTH($C$6),tbContas[Dia do vencimento])<TODAY())) -> 1
B34: Metas
B35: =IFERROR(INDEX(tbMetas[Meta],1),"") -> Reserva de emergência | C35: =IF(B35="","",INDEX(tbMetas[Progresso],1)) -> 0.4
B36: =IFERROR(INDEX(tbMetas[Meta],2),"") -> Viagem de férias | C36: =IF(B36="","",INDEX(tbMetas[Progresso],2)) -> 0.36
B37: =IFERROR(INDEX(tbMetas[Meta],3),"") -> Notebook novo | C37: =IF(B37="","",INDEX(tbMetas[Progresso],3)) -> 0.26666667
B38: =IFERROR(INDEX(tbMetas[Meta],4),"") -> Entrada do apartamento | C38: =IF(B38="","",INDEX(tbMetas[Progresso],4)) -> 0.075
B40: Patrimônio
B41: Patrimônio total | C41: =SUM(tbPatrimonio[Valor atual]) -> 17357.9
B42: Rendimento | C42: =SUM(tbPatrimonio[Rendimento]) -> 757.9
B43: Dívidas (saldo devedor) | C43: =SUM(tbDividas[Saldo devedor]) -> 12045.201
B44: Patrimônio líquido | C44: =C41-C43 -> 5312.6995
B46: Cartão de crédito
B47: Parcelas na fatura do mês | C47: =SUMPRODUCT(tbParcelas[Valor da parcela]*(tbParcelas[1ª fatura]<=$C$6)*(tbParcelas[Última fatura]>=$C$6)) -> 920
B48: Parcelas dos próximos meses | C48: =IFERROR(SUMPRODUCT(tbParcelas[Valor da parcela]*(((((YEAR(tbParcelas[Última fatura])-YEAR($C$6))*12+MONTH(tbParcelas[Última fatura])-MONTH($C$6))>0)*((YEAR(tbParcelas[Última fatura])-YEAR($C$6))*12+MONTH(tbParcelas[Última fatura])-MONTH($C$6)))-(((((YEAR(tbParcelas[Última fatura])-YEAR($C$6))*12+MONTH(tbParcelas[Última fatura])-MONTH($C$6))>0)*((YEAR(tbParcelas[Última fatura])-YEAR($C$6))*12+MONTH(tbParcelas[Última fatura])-MONTH($C$6)))>tbParcelas[Parcelas])*(((((YEAR(tbParcelas[Última fatura])-YEAR($C$6))*12+MONTH(tbParcelas[Última fatura])-MONTH($C$6))>0)*((YEAR(tbParcelas[Última fatura])-YEAR($C$6))*12+MONTH(tbParcelas[Última fatura])-MONTH($C$6)))-tbParcelas[Parcelas]))),0) -> 5800
B50: Para lançar um gasto: toque em "Lançar gasto"
B51: e escreva na primeira linha vazia da tabela.
B53: =HYPERLINK("https://ottavvi.github.io/site-portfolio/","Criado por Otávio · ottavvi.dev") -> Criado por Otávio · ottavvi.dev

Sheet Lançamentos
B1: Lançamentos
B2: Uma linha por entrada ou saída. Valor sempre positivo: o tipo da categoria define se é receita, despesa ou investimento.
B3: =HYPERLINK("#'Painel'!A1","Painel") -> Painel | C3: =HYPERLINK("#'Celular'!A1","Celular") -> Celular | D3: Lançamentos | E3: =HYPERLINK("#'Contas fixas'!A1","Contas") -> Contas | F3: =HYPERLINK("#'Cartão'!A1","Cartão") -> Cartão | G3: =HYPERLINK("#'Dívidas'!A1","Dívidas") -> Dívidas | H3: =HYPERLINK("#'Categorias'!A1","Categorias") -> Categorias | I3: =HYPERLINK("#'Metas'!A1","Metas") -> Metas | J3: =HYPERLINK("#'Patrimônio'!A1","Patrimônio") -> Patrimônio | K3: =HYPERLINK("#'Simulador'!A1","Simulador") -> Simulador | L3: =HYPERLINK("#'Resumo'!A1","Resumo") -> Resumo | M3: =HYPERLINK("#'Como usar'!A1","Ajuda") -> Ajuda
B5: Data | C5: Descrição | D5: Categoria | E5: Valor | F5: Pagamento | G5: Tipo | H5: Grupo | I5: Mês | K5: Como preencher
B6: 46026 | C6: Supermercado | D6: Mercado | E6: 277.48 | F6: Cartão de crédito | G6: =IFERROR(INDEX(tbCategorias[Tipo],MATCH(tbLancamentos[[#This Row],[Categoria]],tbCategorias[Categoria],0)),"Categoria?") -> Despesa | H6: =IFERROR(INDEX(tbCategorias[Grupo],MATCH(tbLancamentos[[#This Row],[Categoria]],tbCategorias[Categoria],0)),"") -> Essencial | I6: =IF(tbLancamentos[[#This Row],[Data]]="","",DATE(YEAR(tbLancamentos[[#This Row],[Data]]),MONTH(tbLancamentos[[#This Row],[Data]]),1)) -> 46023 | K6: Escreva logo abaixo da última linha: a tabela cresce sozinha.
B7: 46026 | C7: Cashback do cartão | D7: Outras receitas | E7: 83.79 | F7: Pix | G7: =IFERROR(INDEX(tbCategorias[Tipo],MATCH(tbLancamentos[[#This Row],[Categoria]],tbCategorias[Categoria],0)),"Categoria?") -> Receita | H7: =IFERROR(INDEX(tbCategorias[Grupo],MATCH(tbLancamentos[[#This Row],[Categoria]],tbCategorias[Categoria],0)),"") -> Renda | I7: =IF(tbLancamentos[[#This Row],[Data]]="","",DATE(YEAR(tbLancamentos[[#This Row],[Data]]),MONTH(tbLancamentos[[#This Row],[Data]]),1)) -> 46023 | K7: Colunas sem cor: você preenche. Colunas cinza-azuladas: calculadas.
B8: 46026 | C8: iFood | D8: Restaurantes e delivery | E8: 32.69 | F8: Pix | G8: =IFERROR(INDEX(tbCategorias[Tipo],MATCH(tbLancamentos[[#This Row],[Categoria]],tbCategorias[Categoria],0)),"Categoria?") -> Despesa | H8: =IFERROR(INDEX(tbCategorias[Grupo],MATCH(tbLancamentos[[#This Row],[Categoria]],tbCategorias[Categoria],0)),"") -> Estilo de vida | I8: =IF(tbLancamentos[[#This Row],[Data]]="","",DATE(YEAR(tbLancamentos[[#This Row],[Data]]),MONTH(tbLancamentos[[#This Row],[Data]]),1)) -> 46023 | K8: Os lançamentos que vêm aqui são fictícios: apague as linhas e use os seus.
B9: 46027 | C9: Salário | D9: Salário | E9: 5800 | F9: Pix | G9: =IFERROR(INDEX(tbCategorias[Tipo],MATCH(tbLancamentos[[#This Row],[Categoria]],tbCategorias[Categoria],0)),"Categoria?") -> Receita | H9: =IFERROR(INDEX(tbCategorias[Grupo],MATCH(tbLancamentos[[#This Row],[Categoria]],tbCategorias[Categoria],0)),"") -> Renda | I9: =IF(tbLancamentos[[#This Row],[Data]]="","",DATE(YEAR(tbLancamentos[[#This Row],[Data]]),MONTH(tbLancamentos[[#This Row],[Data]]),1)) -> 46023
B10: 46028 | C10: Combustível | D10: Transporte | E10: 136.41 | F10: Cartão de crédito | G10: =IFERROR(INDEX(tbCategorias[Tipo],MATCH(tbLancamentos[[#This Row],[Categoria]],tbCategorias[Categoria],0)),"Categoria?") -> Despesa | H10: =IFERROR(INDEX(tbCategorias[Grupo],MATCH(tbLancamentos[[#This Row],[Categoria]],tbCategorias[Categoria],0)),"") -> Essencial | I10: =IF(tbLancamentos[[#This Row],[Data]]="","",DATE(YEAR(tbLancamentos[[#This Row],[Data]]),MONTH(tbLancamentos[[#This Row],[Data]]),1)) -> 46023
B11: 46029 | C11: Aporte reserva de emergência | D11: Investimentos | E11: 600 | F11: Pix | G11: =IFERROR(INDEX(tbCategorias[Tipo],MATCH(tbLancamentos[[#This Row],[Categoria]],tbCategorias[Categoria],0)),"Categoria?") -> Investimento | H11: =IFERROR(INDEX(tbCategorias[Grupo],MATCH(tbLancamentos[[#This Row],[Categoria]],tbCategorias[Categoria],0)),"") -> Investimento | I11: =IF(tbLancamentos[[#This Row],[Data]]="","",DATE(YEAR(tbLancamentos[[#This Row],[Data]]),MONTH(tbLancamentos[[#This Row],[Data]]),1)) -> 46023
B12: 46030 | C12: Passeio | D12: Lazer | E12: 60.11 | F12: Cartão de crédito | G12: =IFERROR(INDEX(tbCategorias[Tipo],MATCH(tbLancamentos[[#This Row],[Categoria]],tbCategorias[Categoria],0)),"Categoria?") -> Despesa | H12: =IFERROR(INDEX(tbCategorias[Grupo],MATCH(tbLancamentos[[#This Row],[Categoria]],tbCategorias[Categoria],0)),"") -> Estilo de vida | I12: =IF(tbLancamentos[[#This Row],[Data]]="","",DATE(YEAR(tbLancamentos[[#This Row],[Data]]),MONTH(tbLancamentos[[#This Row],[Data]]),1)) -> 46023
B13: 46030 | C13: Academia | D13: Saúde | E13: 99.9 | F13: Cartão de crédito | G13: =IFERROR(INDEX(tbCategorias[Tipo],MATCH(tbLancamentos[[#This Row],[Categoria]],tbCategorias[Categoria],0)),"Categoria?") -> Despesa | H13: =IFERROR(INDEX(tbCategorias[Grupo],MATCH(tbLancamentos[[#This Row],[Categoria]],tbCategorias[Categoria],0)),"") -> Essencial | I13: =IF(tbLancamentos[[#This Row],[Data]]="","",DATE(YEAR(tbLancamentos[[#This Row],[Data]]),MONTH(tbLancamentos[[#This Row],[Data]]),1)) -> 46023
B14: 46030 | C14: Lanchonete | D14: Restaurantes e delivery | E14: 103.54 | F14: Cartão de crédito | G14: =IFERROR(INDEX(tbCategorias[Tipo],MATCH(tbLancamentos[[#This Row],[Categoria]],tbCategorias[Categoria],0)),"Categoria?") -> Despesa | H14: =IFERROR(INDEX(tbCategorias[Grupo],MATCH(tbLancamentos[[#This Row],[Categoria]],tbCategorias[Categoria],0)),"") -> Estilo de vida | I14: =IF(tbLancamentos[[#This Row],[Data]]="","",DATE(YEAR(tbLancamentos[[#This Row],[Data]]),MONTH(tbLancamentos[[#This Row],[Data]]),1)) -> 46023
B15: 46030 | C15: Plano odontológico | D15: Saúde | E15: 59.9 | F15: Boleto | G15: =IFERROR(INDEX(tbCategorias[Tipo],MATCH(tbLancamentos[[#This Row],[Categoria]],tbCategorias[Categoria],0)),"Categoria?") -> Despesa | H15: =IFERROR(INDEX(tbCategorias[Grupo],MATCH(tbLancamentos[[#This Row],[Categoria]],tbCategorias[Categoria],0)),"") -> Essencial | I15: =IF(tbLancamentos[[#This Row],[Data]]="","",DATE(YEAR(tbLancamentos[[#This Row],[Data]]),MONTH(tbLancamentos[[#This Row],[Data]]),1)) -> 46023
B16: 46032 | C16: Aluguel | D16: Moradia | E16: 1200 | F16: Boleto | G16: =IFERROR(INDEX(tbCategorias[Tipo],MATCH(tbLancamentos[[#This Row],[Categoria]],tbCategorias[Categoria],0)),"Categoria?") -> Despesa | H16: =IFERROR(INDEX(tbCategorias[Grupo],MATCH(tbLancamentos[[#This Row],[Categoria]],tbCategorias[Categoria],0)),"") -> Essencial | I16: =IF(tbLancamentos[[#This Row],[Data]]="","",DATE(YEAR(tbLancamentos[[#This Row],[Data]]),MONTH(tbLancamentos[[#This Row],[Data]]),1)) -> 46023
B17: 46032 | C17: Feira | D17: Mercado | E17: 180.45 | F17: Débito | G17: =IFERROR(INDEX(tbCategorias[Tipo],MATCH(tbLancamentos[[#This Row],[Categoria]],tbCategorias[Categoria],0)),"Categoria?") -> Despesa | H17: =IFERROR(INDEX(tbCategorias[Grupo],MATCH(tbLancamentos[[#This Row],[Categoria]],tbCategorias[Categoria],0)),"") -> Essencial | I17: =IF(tbLancamentos[[#This Row],[Data]]="","",DATE(YEAR(tbLancamentos[[#This Row],[Data]]),MONTH(tbLancamentos[[#This Row],[Data]]),1)) -> 46023
B18: 46034 | C18: Conta de luz | D18: Contas da casa | E18: 156.26 | F18: Boleto | G18: =IFERROR(INDEX(tbCategorias[Tipo],MATCH(tbLancamentos[[#This Row],[Categoria]],tbCategorias[Categoria],0)),"Categoria?") -> Despesa | H18: =IFERROR(INDEX(tbCategorias[Grupo],MATCH(tbLancamentos[[#This Row],[Categoria]],tbCategorias[Categoria],0)),"") -> Essencial | I18: =IF(tbLancamentos[[#This Row],[Data]]="","",DATE(YEAR(tbLancamentos[[#This Row],[Data]]),MONTH(tbLancamentos[[#This Row],[Data]]),1)) -> 46023
B19: 46035 | C19: Roupas | D19: Compras | E19: 211.33 | F19: Cartão de crédito | G19: =IFERROR(INDEX(tbCategorias[Tipo],MATCH(tbLancamentos[[#This Row],[Categoria]],tbCategorias[Categoria],0)),"Categoria?") -> Despesa | H19: =IFERROR(INDEX(tbCategorias[Grupo],MATCH(tbLancamentos[[#This Row],[Categoria]],tbCategorias[Categoria],0)),"") -> Estilo de vida | I19: =IF(tbLancamentos[[#This Row],[Data]]="","",DATE(YEAR(tbLancamentos[[#This Row],[Data]]),MONTH(tbLancamentos[[#This Row],[Data]]),1)) -> 46023
B20: 46036 | C20: Netflix | D20: Assinaturas | E20: 44.9 | F20: Cartão de crédito | G20: =IFERROR(INDEX(tbCategorias[Tipo],MATCH(tbLancamentos[[#This Row],[Categoria]],tbCategorias[Categoria],0)),"Categoria?") -> Despesa | H20: =IFERROR(INDEX(tbCategorias[Grupo],MATCH(tbLancamentos[[#This Row],[Categoria]],tbCategorias[Categoria],0)),"") -> Estilo de vida | I20: =IF(tbLancamentos[[#This Row],[Data]]="","",DATE(YEAR(tbLancamentos[[#This Row],[Data]]),MONTH(tbLancamentos[[#This Row],[Data]]),1)) -> 46023
... B299: 46320 | C299: Supermercado | D299: Mercado | E299: 120.41 | F299: Cartão de crédito | G299: =IFERROR(INDEX(tbCategorias[Tipo],MATCH(tbLancamentos[[#This Row],[Categoria]],tbCategorias[Categoria],0)),"Categoria?") -> Despesa | H299: =IFERROR(INDEX(tbCategorias[Grupo],MATCH(tbLancamentos[[#This Row],[Categoria]],tbCategorias[Categoria],0)),"") -> Essencial | I299: =IF(tbLancamentos[[#This Row],[Data]]="","",DATE(YEAR(tbLancamentos[[#This Row],[Data]]),MONTH(tbLancamentos[[#This Row],[Data]]),1)) -> 46296

Sheet Contas fixas
B1: Contas fixas
B2: Contas que se repetem todo mês. A situação confere se já existe um lançamento com a mesma descrição no mês escolhido.
B3: =HYPERLINK("#'Painel'!A1","Painel") -> Painel | C3: =HYPERLINK("#'Celular'!A1","Celular") -> Celular | D3: =HYPERLINK("#'Lançamentos'!A1","Lançamentos") -> Lançamentos | E3: Contas | F3: =HYPERLINK("#'Cartão'!A1","Cartão") -> Cartão | G3: =HYPERLINK("#'Dívidas'!A1","Dívidas") -> Dívidas | H3: =HYPERLINK("#'Categorias'!A1","Categorias") -> Categorias | I3: =HYPERLINK("#'Metas'!A1","Metas") -> Metas | J3: =HYPERLINK("#'Patrimônio'!A1","Patrimônio") -> Patrimônio | K3: =HYPERLINK("#'Simulador'!A1","Simulador") -> Simulador | L3: =HYPERLINK("#'Resumo'!A1","Resumo") -> Resumo | M3: =HYPERLINK("#'Como usar'!A1","Ajuda") -> Ajuda
B5: Mês | C5: 46296
B7: Conta | C7: Categoria | D7: Valor previsto | E7: Dia do vencimento | F7: Pagamento | G7: Vence em | H7: Pago no mês | I7: Situação | K7: Resumo do mês
B8: Aluguel | C8: Moradia | D8: 1200 | E8: 10 | F8: Boleto | G8: =DATE(YEAR($C$5),MONTH($C$5),MIN(tbContas[[#This Row],[Dia do vencimento]],DAY(EOMONTH($C$5,0)))) -> 46305 | H8: =SUMIFS(tbLancamentos[Valor],tbLancamentos[Mês],$C$5,tbLancamentos[Descrição],tbContas[[#This Row],[Conta]]) -> 1200 | I8: =IF(tbContas[[#This Row],[Pago no mês]]>0,"✓ Paga",IF(TODAY()>tbContas[[#This Row],[Vence em]],"⚠ Vencida","Pendente")) -> ✓ Paga | K8: Total previsto | L8: =SUM(tbContas[Valor previsto]) -> 1991.3
B9: Conta de luz | C9: Contas da casa | D9: 180 | E9: 12 | F9: Boleto | G9: =DATE(YEAR($C$5),MONTH($C$5),MIN(tbContas[[#This Row],[Dia do vencimento]],DAY(EOMONTH($C$5,0)))) -> 46307 | H9: =SUMIFS(tbLancamentos[Valor],tbLancamentos[Mês],$C$5,tbLancamentos[Descrição],tbContas[[#This Row],[Conta]]) -> 165.63 | I9: =IF(tbContas[[#This Row],[Pago no mês]]>0,"✓ Paga",IF(TODAY()>tbContas[[#This Row],[Vence em]],"⚠ Vencida","Pendente")) -> ✓ Paga | K9: Já pago | L9: =SUM(tbContas[Pago no mês]) -> 1901.55
B10: Conta de água | C10: Contas da casa | D10: 80 | E10: 15 | F10: Boleto | G10: =DATE(YEAR($C$5),MONTH($C$5),MIN(tbContas[[#This Row],[Dia do vencimento]],DAY(EOMONTH($C$5,0)))) -> 46310 | H10: =SUMIFS(tbLancamentos[Valor],tbLancamentos[Mês],$C$5,tbLancamentos[Descrição],tbContas[[#This Row],[Conta]]) -> 79.62 | I10: =IF(tbContas[[#This Row],[Pago no mês]]>0,"✓ Paga",IF(TODAY()>tbContas[[#This Row],[Vence em]],"⚠ Vencida","Pendente")) -> ✓ Paga | K10: Falta pagar | L10: =SUMIFS(tbContas[Valor previsto],tbContas[Situação],"<>✓ Paga") -> 75
B11: Internet | C11: Contas da casa | D11: 99.9 | E11: 18 | F11: Débito | G11: =DATE(YEAR($C$5),MONTH($C$5),MIN(tbContas[[#This Row],[Dia do vencimento]],DAY(EOMONTH($C$5,0)))) -> 46313 | H11: =SUMIFS(tbLancamentos[Valor],tbLancamentos[Mês],$C$5,tbLancamentos[Descrição],tbContas[[#This Row],[Conta]]) -> 99.9 | I11: =IF(tbContas[[#This Row],[Pago no mês]]>0,"✓ Paga",IF(TODAY()>tbContas[[#This Row],[Vence em]],"⚠ Vencida","Pendente")) -> ✓ Paga | K11: Contas pagas | L11: =COUNTIF(tbContas[Situação],"✓ Paga")&" de "&ROWS(tbContas[]) -> 10 de 12
B12: Plano de celular | C12: Contas da casa | D12: 49.9 | E12: 20 | F12: Cartão de crédito | G12: =DATE(YEAR($C$5),MONTH($C$5),MIN(tbContas[[#This Row],[Dia do vencimento]],DAY(EOMONTH($C$5,0)))) -> 46315 | H12: =SUMIFS(tbLancamentos[Valor],tbLancamentos[Mês],$C$5,tbLancamentos[Descrição],tbContas[[#This Row],[Conta]]) -> 49.9 | I12: =IF(tbContas[[#This Row],[Pago no mês]]>0,"✓ Paga",IF(TODAY()>tbContas[[#This Row],[Vence em]],"⚠ Vencida","Pendente")) -> ✓ Paga | K12: Contas vencidas | L12: =COUNTIF(tbContas[Situação],"⚠ Vencida") -> 1
B13: Academia | C13: Saúde | D13: 99.9 | E13: 8 | F13: Cartão de crédito | G13: =DATE(YEAR($C$5),MONTH($C$5),MIN(tbContas[[#This Row],[Dia do vencimento]],DAY(EOMONTH($C$5,0)))) -> 46303 | H13: =SUMIFS(tbLancamentos[Valor],tbLancamentos[Mês],$C$5,tbLancamentos[Descrição],tbContas[[#This Row],[Conta]]) -> 99.9 | I13: =IF(tbContas[[#This Row],[Pago no mês]]>0,"✓ Paga",IF(TODAY()>tbContas[[#This Row],[Vence em]],"⚠ Vencida","Pendente")) -> ✓ Paga
B14: Plano odontológico | C14: Saúde | D14: 59.9 | E14: 8 | F14: Boleto | G14: =DATE(YEAR($C$5),MONTH($C$5),MIN(tbContas[[#This Row],[Dia do vencimento]],DAY(EOMONTH($C$5,0)))) -> 46303 | H14: =SUMIFS(tbLancamentos[Valor],tbLancamentos[Mês],$C$5,tbLancamentos[Descrição],tbContas[[#This Row],[Conta]]) -> 59.9 | I14: =IF(tbContas[[#This Row],[Pago no mês]]>0,"✓ Paga",IF(TODAY()>tbContas[[#This Row],[Vence em]],"⚠ Vencida","Pendente")) -> ✓ Paga | K14: Dica: use na aba Lançamentos a mesma descrição
B15: Netflix | C15: Assinaturas | D15: 44.9 | E15: 14 | F15: Cartão de crédito | G15: =DATE(YEAR($C$5),MONTH($C$5),MIN(tbContas[[#This Row],[Dia do vencimento]],DAY(EOMONTH($C$5,0)))) -> 46309 | H15: =SUMIFS(tbLancamentos[Valor],tbLancamentos[Mês],$C$5,tbLancamentos[Descrição],tbContas[[#This Row],[Conta]]) -> 44.9 | I15: =IF(tbContas[[#This Row],[Pago no mês]]>0,"✓ Paga",IF(TODAY()>tbContas[[#This Row],[Vence em]],"⚠ Vencida","Pendente")) -> ✓ Paga | K15: da conta (ex.: "Conta de luz") para ela
B16: Spotify | C16: Assinaturas | D16: 21.9 | E16: 14 | F16: Cartão de crédito | G16: =DATE(YEAR($C$5),MONTH($C$5),MIN(tbContas[[#This Row],[Dia do vencimento]],DAY(EOMONTH($C$5,0)))) -> 46309 | H16: =SUMIFS(tbLancamentos[Valor],tbLancamentos[Mês],$C$5,tbLancamentos[Descrição],tbContas[[#This Row],[Conta]]) -> 21.9 | I16: =IF(tbContas[[#This Row],[Pago no mês]]>0,"✓ Paga",IF(TODAY()>tbContas[[#This Row],[Vence em]],"⚠ Vencida","Pendente")) -> ✓ Paga | K16: aparecer como paga.
B17: Curso online | C17: Educação | D17: 79.9 | E17: 20 | F17: Cartão de crédito | G17: =DATE(YEAR($C$5),MONTH($C$5),MIN(tbContas[[#This Row],[Dia do vencimento]],DAY(EOMONTH($C$5,0)))) -> 46315 | H17: =SUMIFS(tbLancamentos[Valor],tbLancamentos[Mês],$C$5,tbLancamentos[Descrição],tbContas[[#This Row],[Conta]]) -> 79.9 | I17: =IF(tbContas[[#This Row],[Pago no mês]]>0,"✓ Paga",IF(TODAY()>tbContas[[#This Row],[Vence em]],"⚠ Vencida","Pendente")) -> ✓ Paga
B18: Doação mensal | C18: Outros | D18: 30 | E18: 5 | F18: Pix | G18: =DATE(YEAR($C$5),MONTH($C$5),MIN(tbContas[[#This Row],[Dia do vencimento]],DAY(EOMONTH($C$5,0)))) -> 46300 | H18: =SUMIFS(tbLancamentos[Valor],tbLancamentos[Mês],$C$5,tbLancamentos[Descrição],tbContas[[#This Row],[Conta]]) -> 0 | I18: =IF(tbContas[[#This Row],[Pago no mês]]>0,"✓ Paga",IF(TODAY()>tbContas[[#This Row],[Vence em]],"⚠ Vencida","Pendente")) -> ⚠ Vencida
B19: Seguro residencial | C19: Moradia | D19: 45 | E19: 28 | F19: Débito | G19: =DATE(YEAR($C$5),MONTH($C$5),MIN(tbContas[[#This Row],[Dia do vencimento]],DAY(EOMONTH($C$5,0)))) -> 46323 | H19: =SUMIFS(tbLancamentos[Valor],tbLancamentos[Mês],$C$5,tbLancamentos[Descrição],tbContas[[#This Row],[Conta]]) -> 0 | I19: =IF(tbContas[[#This Row],[Pago no mês]]>0,"✓ Paga",IF(TODAY()>tbContas[[#This Row],[Vence em]],"⚠ Vencida","Pendente")) -> Pendente

Sheet Cartão
B1: Cartão de crédito
B2: Compras parceladas e próximas faturas. A cada mês, lance a parcela em Lançamentos com a mesma descrição da compra para ela aparecer como lançada.
B3: =HYPERLINK("#'Painel'!A1","Painel") -> Painel | C3: =HYPERLINK("#'Celular'!A1","Celular") -> Celular | D3: =HYPERLINK("#'Lançamentos'!A1","Lançamentos") -> Lançamentos | E3: =HYPERLINK("#'Contas fixas'!A1","Contas") -> Contas | F3: Cartão | G3: =HYPERLINK("#'Dívidas'!A1","Dívidas") -> Dívidas | H3: =HYPERLINK("#'Categorias'!A1","Categorias") -> Categorias | I3: =HYPERLINK("#'Metas'!A1","Metas") -> Metas | J3: =HYPERLINK("#'Patrimônio'!A1","Patrimônio") -> Patrimônio | K3: =HYPERLINK("#'Simulador'!A1","Simulador") -> Simulador | L3: =HYPERLINK("#'Resumo'!A1","Resumo") -> Resumo | M3: =HYPERLINK("#'Como usar'!A1","Ajuda") -> Ajuda
B5: Mês | C5: 46296
B7: Cartão | C7: Fecha dia | D7: Vence dia | E7: Limite | G7: Cartão | H7: Parcelas no mês | I7: Ainda a pagar | J7: Limite | K7: Limite livre | M7: Fatura | N7: =IFERROR(INDEX(tbCartoes[Cartão],COLUMNS($N7:N7)),"") -> Nubank | O7: =IFERROR(INDEX(tbCartoes[Cartão],COLUMNS($N7:O7)),"") -> Inter | P7: =IFERROR(INDEX(tbCartoes[Cartão],COLUMNS($N7:P7)),"") | Q7: Total
B8: Nubank | C8: 3 | D8: 10 | E8: 6000 | G8: =IFERROR(INDEX(tbCartoes[Cartão],ROWS(G$8:G8)),"") -> Nubank | H8: =IF($G8="","",SUMIFS(tbParcelas[Valor no mês],tbParcelas[Cartão],$G8)) -> 720 | I8: =IF($G8="","",H8+SUMIFS(tbParcelas[A pagar depois],tbParcelas[Cartão],$G8)) -> 5520 | J8: =IF($G8="","",INDEX(tbCartoes[Limite],MATCH($G8,tbCartoes[Cartão],0))) -> 6000 | K8: =IF($G8="","",J8-I8) -> 480 | M8: =$C$5 -> 46296 | N8: =IF(N$7="","",SUMPRODUCT(tbParcelas[Valor da parcela]*(tbParcelas[Cartão]=N$7)*(tbParcelas[1ª fatura]<=$M8)*(tbParcelas[Última fatura]>=$M8))) -> 720 | O8: =IF(O$7="","",SUMPRODUCT(tbParcelas[Valor da parcela]*(tbParcelas[Cartão]=O$7)*(tbParcelas[1ª fatura]<=$M8)*(tbParcelas[Última fatura]>=$M8))) -> 200 | P8: =IF(P$7="","",SUMPRODUCT(tbParcelas[Valor da parcela]*(tbParcelas[Cartão]=P$7)*(tbParcelas[1ª fatura]<=$M8)*(tbParcelas[Última fatura]>=$M8))) | Q8: =SUM(N8:P8) -> 920
B9: Inter | C9: 25 | D9: 5 | E9: 3000 | G9: =IFERROR(INDEX(tbCartoes[Cartão],ROWS(G$8:G9)),"") -> Inter | H9: =IF($G9="","",SUMIFS(tbParcelas[Valor no mês],tbParcelas[Cartão],$G9)) -> 200 | I9: =IF($G9="","",H9+SUMIFS(tbParcelas[A pagar depois],tbParcelas[Cartão],$G9)) -> 1200 | J9: =IF($G9="","",INDEX(tbCartoes[Limite],MATCH($G9,tbCartoes[Cartão],0))) -> 3000 | K9: =IF($G9="","",J9-I9) -> 1800 | M9: =EDATE(M8,1) -> 46327 | N9: =IF(N$7="","",SUMPRODUCT(tbParcelas[Valor da parcela]*(tbParcelas[Cartão]=N$7)*(tbParcelas[1ª fatura]<=$M9)*(tbParcelas[Última fatura]>=$M9))) -> 720 | O9: =IF(O$7="","",SUMPRODUCT(tbParcelas[Valor da parcela]*(tbParcelas[Cartão]=O$7)*(tbParcelas[1ª fatura]<=$M9)*(tbParcelas[Última fatura]>=$M9))) -> 200 | P9: =IF(P$7="","",SUMPRODUCT(tbParcelas[Valor da parcela]*(tbParcelas[Cartão]=P$7)*(tbParcelas[1ª fatura]<=$M9)*(tbParcelas[Última fatura]>=$M9))) | Q9: =SUM(N9:P9) -> 920
G10: =IFERROR(INDEX(tbCartoes[Cartão],ROWS(G$8:G10)),"") | H10: =IF($G10="","",SUMIFS(tbParcelas[Valor no mês],tbParcelas[Cartão],$G10)) | I10: =IF($G10="","",H10+SUMIFS(tbParcelas[A pagar depois],tbParcelas[Cartão],$G10)) | J10: =IF($G10="","",INDEX(tbCartoes[Limite],MATCH($G10,tbCartoes[Cartão],0))) | K10: =IF($G10="","",J10-I10) | M10: =EDATE(M9,1) -> 46357 | N10: =IF(N$7="","",SUMPRODUCT(tbParcelas[Valor da parcela]*(tbParcelas[Cartão]=N$7)*(tbParcelas[1ª fatura]<=$M10)*(tbParcelas[Última fatura]>=$M10))) -> 720 | O10: =IF(O$7="","",SUMPRODUCT(tbParcelas[Valor da parcela]*(tbParcelas[Cartão]=O$7)*(tbParcelas[1ª fatura]<=$M10)*(tbParcelas[Última fatura]>=$M10))) -> 200 | P10: =IF(P$7="","",SUMPRODUCT(tbParcelas[Valor da parcela]*(tbParcelas[Cartão]=P$7)*(tbParcelas[1ª fatura]<=$M10)*(tbParcelas[Última fatura]>=$M10))) | Q10: =SUM(N10:P10) -> 920
G11: Total | H11: =SUM(H8:H10) -> 920 | I11: =SUM(I8:I10) -> 6720 | J11: =SUM(J8:J10) -> 9000 | K11: =SUM(K8:K10) -> 2280 | M11: =EDATE(M10,1) -> 46388 | N11: =IF(N$7="","",SUMPRODUCT(tbParcelas[Valor da parcela]*(tbParcelas[Cartão]=N$7)*(tbParcelas[1ª fatura]<=$M11)*(tbParcelas[Última fatura]>=$M11))) -> 560 | O11: =IF(O$7="","",SUMPRODUCT(tbParcelas[Valor da parcela]*(tbParcelas[Cartão]=O$7)*(tbParcelas[1ª fatura]<=$M11)*(tbParcelas[Última fatura]>=$M11))) -> 200 | P11: =IF(P$7="","",SUMPRODUCT(tbParcelas[Valor da parcela]*(tbParcelas[Cartão]=P$7)*(tbParcelas[1ª fatura]<=$M11)*(tbParcelas[Última fatura]>=$M11))) | Q11: =SUM(N11:P11) -> 760
M12: =EDATE(M11,1) -> 46419 | N12: =IF(N$7="","",SUMPRODUCT(tbParcelas[Valor da parcela]*(tbParcelas[Cartão]=N$7)*(tbParcelas[1ª fatura]<=$M12)*(tbParcelas[Última fatura]>=$M12))) -> 560 | O12: =IF(O$7="","",SUMPRODUCT(tbParcelas[Valor da parcela]*(tbParcelas[Cartão]=O$7)*(tbParcelas[1ª fatura]<=$M12)*(tbParcelas[Última fatura]>=$M12))) -> 200 | P12: =IF(P$7="","",SUMPRODUCT(tbParcelas[Valor da parcela]*(tbParcelas[Cartão]=P$7)*(tbParcelas[1ª fatura]<=$M12)*(tbParcelas[Última fatura]>=$M12))) | Q12: =SUM(N12:P12) -> 760
G13: Ainda a pagar = parcelas do mês + parcelas dos meses seguintes. Limite livre não desconta as compras à vista do mês. | M13: =EDATE(M12,1) -> 46447 | N13: =IF(N$7="","",SUMPRODUCT(tbParcelas[Valor da parcela]*(tbParcelas[Cartão]=N$7)*(tbParcelas[1ª fatura]<=$M13)*(tbParcelas[Última fatura]>=$M13))) -> 560 | O13: =IF(O$7="","",SUMPRODUCT(tbParcelas[Valor da parcela]*(tbParcelas[Cartão]=O$7)*(tbParcelas[1ª fatura]<=$M13)*(tbParcelas[Última fatura]>=$M13))) -> 200 | P13: =IF(P$7="","",SUMPRODUCT(tbParcelas[Valor da parcela]*(tbParcelas[Cartão]=P$7)*(tbParcelas[1ª fatura]<=$M13)*(tbParcelas[Última fatura]>=$M13))) | Q13: =SUM(N13:P13) -> 760
M14: =EDATE(M13,1) -> 46478 | N14: =IF(N$7="","",SUMPRODUCT(tbParcelas[Valor da parcela]*(tbParcelas[Cartão]=N$7)*(tbParcelas[1ª fatura]<=$M14)*(tbParcelas[Última fatura]>=$M14))) -> 560 | O14: =IF(O$7="","",SUMPRODUCT(tbParcelas[Valor da parcela]*(tbParcelas[Cartão]=O$7)*(tbParcelas[1ª fatura]<=$M14)*(tbParcelas[Última fatura]>=$M14))) -> 0 | P14: =IF(P$7="","",SUMPRODUCT(tbParcelas[Valor da parcela]*(tbParcelas[Cartão]=P$7)*(tbParcelas[1ª fatura]<=$M14)*(tbParcelas[Última fatura]>=$M14))) | Q14: =SUM(N14:P14) -> 560
M15: =EDATE(M14,1) -> 46508 | N15: =IF(N$7="","",SUMPRODUCT(tbParcelas[Valor da parcela]*(tbParcelas[Cartão]=N$7)*(tbParcelas[1ª fatura]<=$M15)*(tbParcelas[Última fatura]>=$M15))) -> 560 | O15: =IF(O$7="","",SUMPRODUCT(tbParcelas[Valor da parcela]*(tbParcelas[Cartão]=O$7)*(tbParcelas[1ª fatura]<=$M15)*(tbParcelas[Última fatura]>=$M15))) -> 0 | P15: =IF(P$7="","",SUMPRODUCT(tbParcelas[Valor da parcela]*(tbParcelas[Cartão]=P$7)*(tbParcelas[1ª fatura]<=$M15)*(tbParcelas[Última fatura]>=$M15))) | Q15: =SUM(N15:P15) -> 560
M16: =EDATE(M15,1) -> 46539 | N16: =IF(N$7="","",SUMPRODUCT(tbParcelas[Valor da parcela]*(tbParcelas[Cartão]=N$7)*(tbParcelas[1ª fatura]<=$M16)*(tbParcelas[Última fatura]>=$M16))) -> 560 | O16: =IF(O$7="","",SUMPRODUCT(tbParcelas[Valor da parcela]*(tbParcelas[Cartão]=O$7)*(tbParcelas[1ª fatura]<=$M16)*(tbParcelas[Última fatura]>=$M16))) -> 0 | P16: =IF(P$7="","",SUMPRODUCT(tbParcelas[Valor da parcela]*(tbParcelas[Cartão]=P$7)*(tbParcelas[1ª fatura]<=$M16)*(tbParcelas[Última fatura]>=$M16))) | Q16: =SUM(N16:P16) -> 560
M17: =EDATE(M16,1) -> 46569 | N17: =IF(N$7="","",SUMPRODUCT(tbParcelas[Valor da parcela]*(tbParcelas[Cartão]=N$7)*(tbParcelas[1ª fatura]<=$M17)*(tbParcelas[Última fatura]>=$M17))) -> 0 | O17: =IF(O$7="","",SUMPRODUCT(tbParcelas[Valor da parcela]*(tbParcelas[Cartão]=O$7)*(tbParcelas[1ª fatura]<=$M17)*(tbParcelas[Última fatura]>=$M17))) -> 0 | P17: =IF(P$7="","",SUMPRODUCT(tbParcelas[Valor da parcela]*(tbParcelas[Cartão]=P$7)*(tbParcelas[1ª fatura]<=$M17)*(tbParcelas[Última fatura]>=$M17))) | Q17: =SUM(N17:P17) -> 0
M18: =EDATE(M17,1) -> 46600 | N18: =IF(N$7="","",SUMPRODUCT(tbParcelas[Valor da parcela]*(tbParcelas[Cartão]=N$7)*(tbParcelas[1ª fatura]<=$M18)*(tbParcelas[Última fatura]>=$M18))) -> 0 | O18: =IF(O$7="","",SUMPRODUCT(tbParcelas[Valor da parcela]*(tbParcelas[Cartão]=O$7)*(tbParcelas[1ª fatura]<=$M18)*(tbParcelas[Última fatura]>=$M18))) -> 0 | P18: =IF(P$7="","",SUMPRODUCT(tbParcelas[Valor da parcela]*(tbParcelas[Cartão]=P$7)*(tbParcelas[1ª fatura]<=$M18)*(tbParcelas[Última fatura]>=$M18))) | Q18: =SUM(N18:P18) -> 0
M19: =EDATE(M18,1) -> 46631 | N19: =IF(N$7="","",SUMPRODUCT(tbParcelas[Valor da parcela]*(tbParcelas[Cartão]=N$7)*(tbParcelas[1ª fatura]<=$M19)*(tbParcelas[Última fatura]>=$M19))) -> 0 | O19: =IF(O$7="","",SUMPRODUCT(tbParcelas[Valor da parcela]*(tbParcelas[Cartão]=O$7)*(tbParcelas[1ª fatura]<=$M19)*(tbParcelas[Última fatura]>=$M19))) -> 0 | P19: =IF(P$7="","",SUMPRODUCT(tbParcelas[Valor da parcela]*(tbParcelas[Cartão]=P$7)*(tbParcelas[1ª fatura]<=$M19)*(tbParcelas[Última fatura]>=$M19))) | Q19: =SUM(N19:P19) -> 0
B21: Compras parceladas
B22: Data da compra | C22: Descrição | D22: Categoria | E22: Cartão | F22: Valor total | G22: Parcelas | H22: Valor da parcela | I22: 1ª fatura | J22: Última fatura | K22: Parcela do mês | L22: Valor no mês | M22: A pagar depois | N22: Situação
B23: 46183 | C23: Celular novo | D23: Compras | E23: Nubank | F23: 2400 | G23: 12 | H23: =IF(N(tbParcelas[[#This Row],[Parcelas]])=0,0,tbParcelas[[#This Row],[Valor total]]/tbParcelas[[#This Row],[Parcelas]]) -> 200 | I23: =IFERROR(EDATE(DATE(YEAR(tbParcelas[[#This Row],[Data da compra]]),MONTH(tbParcelas[[#This Row],[Data da compra]]),1),IF(DAY(tbParcelas[[#This Row],[Data da compra]])>=INDEX(tbCartoes[Fecha dia],MATCH(tbParcelas[[#This Row],[Cartão]],tbCartoes[Cartão],0)),1,0)+IF(INDEX(tbCartoes[Vence dia],MATCH(tbParcelas[[#This Row],[Cartão]],tbCartoes[Cartão],0))<=INDEX(tbCartoes[Fecha dia],MATCH(tbParcelas[[#This Row],[Cartão]],tbCartoes[Cartão],0)),1,0)),"") -> 46204 | J23: =IF(tbParcelas[[#This Row],[1ª fatura]]="","",EDATE(tbParcelas[[#This Row],[1ª fatura]],tbParcelas[[#This Row],[Parcelas]]-1)) -> 46539 | K23: =IF(tbParcelas[[#This Row],[1ª fatura]]="","",IF(AND($C$5>=tbParcelas[[#This Row],[1ª fatura]],$C$5<=tbParcelas[[#This Row],[Última fatura]]),((YEAR($C$5)-YEAR(tbParcelas[[#This Row],[1ª fatura]]))*12+MONTH($C$5)-MONTH(tbParcelas[[#This Row],[1ª fatura]])+1)&" de "&tbParcelas[[#This Row],[Parcelas]],"—")) -> 4 de 12 | L23: =IF(tbParcelas[[#This Row],[1ª fatura]]="",0,IF(AND($C$5>=tbParcelas[[#This Row],[1ª fatura]],$C$5<=tbParcelas[[#This Row],[Última fatura]]),tbParcelas[[#This Row],[Valor da parcela]],0)) -> 200 | M23: =IF(tbParcelas[[#This Row],[1ª fatura]]="",0,tbParcelas[[#This Row],[Valor da parcela]]*MAX(0,MIN(tbParcelas[[#This Row],[Parcelas]],(YEAR(tbParcelas[[#This Row],[Última fatura]])-YEAR($C$5))*12+MONTH(tbParcelas[[#This Row],[Última fatura]])-MONTH($C$5)))) -> 1600 | N23: =IF(tbParcelas[[#This Row],[Valor no mês]]=0,"—",IF(SUMIFS(tbLancamentos[Valor],tbLancamentos[Mês],$C$5,tbLancamentos[Descrição],tbParcelas[[#This Row],[Descrição]])>0,"✓ Lançada","Lançar no mês")) -> Lançar no mês
B24: 46249 | C24: Geladeira | D24: Compras | E24: Nubank | F24: 3600 | G24: 10 | H24: =IF(N(tbParcelas[[#This Row],[Parcelas]])=0,0,tbParcelas[[#This Row],[Valor total]]/tbParcelas[[#This Row],[Parcelas]]) -> 360 | I24: =IFERROR(EDATE(DATE(YEAR(tbParcelas[[#This Row],[Data da compra]]),MONTH(tbParcelas[[#This Row],[Data da compra]]),1),IF(DAY(tbParcelas[[#This Row],[Data da compra]])>=INDEX(tbCartoes[Fecha dia],MATCH(tbParcelas[[#This Row],[Cartão]],tbCartoes[Cartão],0)),1,0)+IF(INDEX(tbCartoes[Vence dia],MATCH(tbParcelas[[#This Row],[Cartão]],tbCartoes[Cartão],0))<=INDEX(tbCartoes[Fecha dia],MATCH(tbParcelas[[#This Row],[Cartão]],tbCartoes[Cartão],0)),1,0)),"") -> 46266 | J24: =IF(tbParcelas[[#This Row],[1ª fatura]]="","",EDATE(tbParcelas[[#This Row],[1ª fatura]],tbParcelas[[#This Row],[Parcelas]]-1)) -> 46539 | K24: =IF(tbParcelas[[#This Row],[1ª fatura]]="","",IF(AND($C$5>=tbParcelas[[#This Row],[1ª fatura]],$C$5<=tbParcelas[[#This Row],[Última fatura]]),((YEAR($C$5)-YEAR(tbParcelas[[#This Row],[1ª fatura]]))*12+MONTH($C$5)-MONTH(tbParcelas[[#This Row],[1ª fatura]])+1)&" de "&tbParcelas[[#This Row],[Parcelas]],"—")) -> 2 de 10 | L24: =IF(tbParcelas[[#This Row],[1ª fatura]]="",0,IF(AND($C$5>=tbParcelas[[#This Row],[1ª fatura]],$C$5<=tbParcelas[[#This Row],[Última fatura]]),tbParcelas[[#This Row],[Valor da parcela]],0)) -> 360 | M24: =IF(tbParcelas[[#This Row],[1ª fatura]]="",0,tbParcelas[[#This Row],[Valor da parcela]]*MAX(0,MIN(tbParcelas[[#This Row],[Parcelas]],(YEAR(tbParcelas[[#This Row],[Última fatura]])-YEAR($C$5))*12+MONTH(tbParcelas[[#This Row],[Última fatura]])-MONTH($C$5)))) -> 2880 | N24: =IF(tbParcelas[[#This Row],[Valor no mês]]=0,"—",IF(SUMIFS(tbLancamentos[Valor],tbLancamentos[Mês],$C$5,tbLancamentos[Descrição],tbParcelas[[#This Row],[Descrição]])>0,"✓ Lançada","Lançar no mês")) -> Lançar no mês
B25: 46285 | C25: Curso de inglês | D25: Educação | E25: Inter | F25: 1200 | G25: 6 | H25: =IF(N(tbParcelas[[#This Row],[Parcelas]])=0,0,tbParcelas[[#This Row],[Valor total]]/tbParcelas[[#This Row],[Parcelas]]) -> 200 | I25: =IFERROR(EDATE(DATE(YEAR(tbParcelas[[#This Row],[Data da compra]]),MONTH(tbParcelas[[#This Row],[Data da compra]]),1),IF(DAY(tbParcelas[[#This Row],[Data da compra]])>=INDEX(tbCartoes[Fecha dia],MATCH(tbParcelas[[#This Row],[Cartão]],tbCartoes[Cartão],0)),1,0)+IF(INDEX(tbCartoes[Vence dia],MATCH(tbParcelas[[#This Row],[Cartão]],tbCartoes[Cartão],0))<=INDEX(tbCartoes[Fecha dia],MATCH(tbParcelas[[#This Row],[Cartão]],tbCartoes[Cartão],0)),1,0)),"") -> 46296 | J25: =IF(tbParcelas[[#This Row],[1ª fatura]]="","",EDATE(tbParcelas[[#This Row],[1ª fatura]],tbParcelas[[#This Row],[Parcelas]]-1)) -> 46447 | K25: =IF(tbParcelas[[#This Row],[1ª fatura]]="","",IF(AND($C$5>=tbParcelas[[#This Row],[1ª fatura]],$C$5<=tbParcelas[[#This Row],[Última fatura]]),((YEAR($C$5)-YEAR(tbParcelas[[#This Row],[1ª fatura]]))*12+MONTH($C$5)-MONTH(tbParcelas[[#This Row],[1ª fatura]])+1)&" de "&tbParcelas[[#This Row],[Parcelas]],"—")) -> 1 de 6 | L25: =IF(tbParcelas[[#This Row],[1ª fatura]]="",0,IF(AND($C$5>=tbParcelas[[#This Row],[1ª fatura]],$C$5<=tbParcelas[[#This Row],[Última fatura]]),tbParcelas[[#This Row],[Valor da parcela]],0)) -> 200 | M25: =IF(tbParcelas[[#This Row],[1ª fatura]]="",0,tbParcelas[[#This Row],[Valor da parcela]]*MAX(0,MIN(tbParcelas[[#This Row],[Parcelas]],(YEAR(tbParcelas[[#This Row],[Última fatura]])-YEAR($C$5))*12+MONTH(tbParcelas[[#This Row],[Última fatura]])-MONTH($C$5)))) -> 1000 | N25: =IF(tbParcelas[[#This Row],[Valor no mês]]=0,"—",IF(SUMIFS(tbLancamentos[Valor],tbLancamentos[Mês],$C$5,tbLancamentos[Descrição],tbParcelas[[#This Row],[Descrição]])>0,"✓ Lançada","Lançar no mês")) -> Lançar no mês
B26: 46297 | C26: Tênis de corrida | D26: Compras | E26: Nubank | F26: 480 | G26: 3 | H26: =IF(N(tbParcelas[[#This Row],[Parcelas]])=0,0,tbParcelas[[#This Row],[Valor total]]/tbParcelas[[#This Row],[Parcelas]]) -> 160 | I26: =IFERROR(EDATE(DATE(YEAR(tbParcelas[[#This Row],[Data da compra]]),MONTH(tbParcelas[[#This Row],[Data da compra]]),1),IF(DAY(tbParcelas[[#This Row],[Data da compra]])>=INDEX(tbCartoes[Fecha dia],MATCH(tbParcelas[[#This Row],[Cartão]],tbCartoes[Cartão],0)),1,0)+IF(INDEX(tbCartoes[Vence dia],MATCH(tbParcelas[[#This Row],[Cartão]],tbCartoes[Cartão],0))<=INDEX(tbCartoes[Fecha dia],MATCH(tbParcelas[[#This Row],[Cartão]],tbCartoes[Cartão],0)),1,0)),"") -> 46296 | J26: =IF(tbParcelas[[#This Row],[1ª fatura]]="","",EDATE(tbParcelas[[#This Row],[1ª fatura]],tbParcelas[[#This Row],[Parcelas]]-1)) -> 46357 | K26: =IF(tbParcelas[[#This Row],[1ª fatura]]="","",IF(AND($C$5>=tbParcelas[[#This Row],[1ª fatura]],$C$5<=tbParcelas[[#This Row],[Última fatura]]),((YEAR($C$5)-YEAR(tbParcelas[[#This Row],[1ª fatura]]))*12+MONTH($C$5)-MONTH(tbParcelas[[#This Row],[1ª fatura]])+1)&" de "&tbParcelas[[#This Row],[Parcelas]],"—")) -> 1 de 3 | L26: =IF(tbParcelas[[#This Row],[1ª fatura]]="",0,IF(AND($C$5>=tbParcelas[[#This Row],[1ª fatura]],$C$5<=tbParcelas[[#This Row],[Última fatura]]),tbParcelas[[#This Row],[Valor da parcela]],0)) -> 160 | M26: =IF(tbParcelas[[#This Row],[1ª fatura]]="",0,tbParcelas[[#This Row],[Valor da parcela]]*MAX(0,MIN(tbParcelas[[#This Row],[Parcelas]],(YEAR(tbParcelas[[#This Row],[Última fatura]])-YEAR($C$5))*12+MONTH(tbParcelas[[#This Row],[Última fatura]])-MONTH($C$5)))) -> 320 | N26: =IF(tbParcelas[[#This Row],[Valor no mês]]=0,"—",IF(SUMIFS(tbLancamentos[Valor],tbLancamentos[Mês],$C$5,tbLancamentos[Descrição],tbParcelas[[#This Row],[Descrição]])>0,"✓ Lançada","Lançar no mês")) -> Lançar no mês

Sheet Dívidas
B1: Dívidas e empréstimos
B2: Financiamentos, empréstimos e parcelamentos com juros. Atualize "Parcelas pagas" a cada mês.
B3: =HYPERLINK("#'Painel'!A1","Painel") -> Painel | C3: =HYPERLINK("#'Celular'!A1","Celular") -> Celular | D3: =HYPERLINK("#'Lançamentos'!A1","Lançamentos") -> Lançamentos | E3: =HYPERLINK("#'Contas fixas'!A1","Contas") -> Contas | F3: =HYPERLINK("#'Cartão'!A1","Cartão") -> Cartão | G3: Dívidas | H3: =HYPERLINK("#'Categorias'!A1","Categorias") -> Categorias | I3: =HYPERLINK("#'Metas'!A1","Metas") -> Metas | J3: =HYPERLINK("#'Patrimônio'!A1","Patrimônio") -> Patrimônio | K3: =HYPERLINK("#'Simulador'!A1","Simulador") -> Simulador | L3: =HYPERLINK("#'Resumo'!A1","Resumo") -> Resumo | M3: =HYPERLINK("#'Como usar'!A1","Ajuda") -> Ajuda
B5: Dívida | C5: Credor | D5: Valor contratado | E5: Juros ao mês | F5: Nº de parcelas | G5: Valor da parcela | H5: 1ª parcela | I5: Parcelas pagas | J5: Restantes | K5: Saldo devedor | L5: Total a pagar | M5: Juros a pagar | N5: Quitação | O5: Progresso | Q5: Dívida | R5: Já pago | S5: Falta pagar
B6: Financiamento do carro | C6: Banco do Brasil | D6: 18000 | E6: 0.0129 | F6: 36 | G6: 640 | H6: 45726 | I6: 19 | J6: =MAX(0,tbDividas[[#This Row],[Nº de parcelas]]-tbDividas[[#This Row],[Parcelas pagas]]) -> 17 | K6: =IF(tbDividas[[#This Row],[Restantes]]=0,0,IF(N(tbDividas[[#This Row],[Juros ao mês]])=0,tbDividas[[#This Row],[Valor da parcela]]*tbDividas[[#This Row],[Restantes]],PV(tbDividas[[#This Row],[Juros ao mês]],tbDividas[[#This Row],[Restantes]],-tbDividas[[#This Row],[Valor da parcela]]))) -> 9713.7207 | L6: =tbDividas[[#This Row],[Valor da parcela]]*tbDividas[[#This Row],[Restantes]] -> 10880 | M6: =tbDividas[[#This Row],[Total a pagar]]-tbDividas[[#This Row],[Saldo devedor]] -> 1166.2793 | N6: =IF(tbDividas[[#This Row],[1ª parcela]]="","",EDATE(tbDividas[[#This Row],[1ª parcela]],tbDividas[[#This Row],[Nº de parcelas]]-1)) -> 46793 | O6: =IF(N(tbDividas[[#This Row],[Nº de parcelas]])=0,"",tbDividas[[#This Row],[Parcelas pagas]]/tbDividas[[#This Row],[Nº de parcelas]]) -> 0.52777778 | Q6: =IFERROR(INDEX(tbDividas[Dívida],ROWS(Q$6:Q6)),"") -> Financiamento do carro | R6: =IF($Q6="","",INDEX(tbDividas[Valor da parcela],ROWS(R$6:R6))*INDEX(tbDividas[Parcelas pagas],ROWS(R$6:R6))) -> 12160 | S6: =IF($Q6="","",INDEX(tbDividas[Total a pagar],ROWS(S$6:S6))) -> 10880
B7: Empréstimo pessoal | C7: Nubank | D7: 5000 | E7: 0.032 | F7: 12 | G7: 512 | H7: 46117 | I7: 7 | J7: =MAX(0,tbDividas[[#This Row],[Nº de parcelas]]-tbDividas[[#This Row],[Parcelas pagas]]) -> 5 | K7: =IF(tbDividas[[#This Row],[Restantes]]=0,0,IF(N(tbDividas[[#This Row],[Juros ao mês]])=0,tbDividas[[#This Row],[Valor da parcela]]*tbDividas[[#This Row],[Restantes]],PV(tbDividas[[#This Row],[Juros ao mês]],tbDividas[[#This Row],[Restantes]],-tbDividas[[#This Row],[Valor da parcela]]))) -> 2331.4799 | L7: =tbDividas[[#This Row],[Valor da parcela]]*tbDividas[[#This Row],[Restantes]] -> 2560 | M7: =tbDividas[[#This Row],[Total a pagar]]-tbDividas[[#This Row],[Saldo devedor]] -> 228.52011 | N7: =IF(tbDividas[[#This Row],[1ª parcela]]="","",EDATE(tbDividas[[#This Row],[1ª parcela]],tbDividas[[#This Row],[Nº de parcelas]]-1)) -> 46451 | O7: =IF(N(tbDividas[[#This Row],[Nº de parcelas]])=0,"",tbDividas[[#This Row],[Parcelas pagas]]/tbDividas[[#This Row],[Nº de parcelas]]) -> 0.58333333 | Q7: =IFERROR(INDEX(tbDividas[Dívida],ROWS(Q$6:Q7)),"") -> Empréstimo pessoal | R7: =IF($Q7="","",INDEX(tbDividas[Valor da parcela],ROWS(R$6:R7))*INDEX(tbDividas[Parcelas pagas],ROWS(R$6:R7))) -> 3584 | S7: =IF($Q7="","",INDEX(tbDividas[Total a pagar],ROWS(S$6:S7))) -> 2560
Q8: =IFERROR(INDEX(tbDividas[Dívida],ROWS(Q$6:Q8)),"") | R8: =IF($Q8="","",INDEX(tbDividas[Valor da parcela],ROWS(R$6:R8))*INDEX(tbDividas[Parcelas pagas],ROWS(R$6:R8))) | S8: =IF($Q8="","",INDEX(tbDividas[Total a pagar],ROWS(S$6:S8)))
B12: Resumo das dívidas
B13: Saldo devedor (quitar hoje) | C13: =SUM(tbDividas[Saldo devedor]) -> 12045.201
B14: Parcelas por mês | C14: =SUMIFS(tbDividas[Valor da parcela],tbDividas[Restantes],">0") -> 1152
B15: Total que ainda vai pagar | C15: =SUM(tbDividas[Total a pagar]) -> 13440
B16: Juros que ainda vai pagar | C16: =SUM(tbDividas[Juros a pagar]) -> 1394.7995
B17: % da renda nas parcelas | C17: =IFERROR(C14/AVERAGEIF(Resumo!$C$7:$C$18,">0"),"") -> 0.1883686
B18: Última quitação | C18: =IF(COUNT(tbDividas[Quitação])=0,"",MAX(tbDividas[Quitação])) -> 46793
B20: Saldo devedor = quanto custaria quitar tudo hoje (parcelas restantes trazidas a valor presente pelos juros).
B21: Quitar antes economiza os "juros que ainda vai pagar". Acima de 30% da renda em parcelas é sinal de alerta.

Sheet Categorias
B1: Categorias
B2: Ajuste nomes, tipo, grupo e orçamento. Categorias novas entram nas listas e no painel sozinhas.
B3: =HYPERLINK("#'Painel'!A1","Painel") -> Painel | C3: =HYPERLINK("#'Celular'!A1","Celular") -> Celular | D3: =HYPERLINK("#'Lançamentos'!A1","Lançamentos") -> Lançamentos | E3: =HYPERLINK("#'Contas fixas'!A1","Contas") -> Contas | F3: =HYPERLINK("#'Cartão'!A1","Cartão") -> Cartão | G3: =HYPERLINK("#'Dívidas'!A1","Dívidas") -> Dívidas | H3: Categorias | I3: =HYPERLINK("#'Metas'!A1","Metas") -> Metas | J3: =HYPERLINK("#'Patrimônio'!A1","Patrimônio") -> Patrimônio | K3: =HYPERLINK("#'Simulador'!A1","Simulador") -> Simulador | L3: =HYPERLINK("#'Resumo'!A1","Resumo") -> Resumo | M3: =HYPERLINK("#'Como usar'!A1","Ajuda") -> Ajuda
B5: Categoria | C5: Tipo | D5: Grupo | E5: Orçamento mensal | F5: Ordem | H5: Listas usadas nas validações
B6: Salário | C6: Receita | D6: Renda | F6: =IF(tbCategorias[[#This Row],[Tipo]]="Receita","",COUNTIF(INDEX(tbCategorias[Tipo],1):tbCategorias[[#This Row],[Tipo]],"<>Receita")) | H6: Tipos | I6: Grupos | J6: Pagamento
B7: Freelance | C7: Receita | D7: Renda | F7: =IF(tbCategorias[[#This Row],[Tipo]]="Receita","",COUNTIF(INDEX(tbCategorias[Tipo],1):tbCategorias[[#This Row],[Tipo]],"<>Receita")) | H7: Receita | I7: Renda | J7: Pix
B8: Outras receitas | C8: Receita | D8: Renda | F8: =IF(tbCategorias[[#This Row],[Tipo]]="Receita","",COUNTIF(INDEX(tbCategorias[Tipo],1):tbCategorias[[#This Row],[Tipo]],"<>Receita")) | H8: Despesa | I8: Essencial | J8: Cartão de crédito
B9: Moradia | C9: Despesa | D9: Essencial | E9: 1200 | F9: =IF(tbCategorias[[#This Row],[Tipo]]="Receita","",COUNTIF(INDEX(tbCategorias[Tipo],1):tbCategorias[[#This Row],[Tipo]],"<>Receita")) -> 1 | H9: Investimento | I9: Estilo de vida | J9: Débito
B10: Contas da casa | C10: Despesa | D10: Essencial | E10: 420 | F10: =IF(tbCategorias[[#This Row],[Tipo]]="Receita","",COUNTIF(INDEX(tbCategorias[Tipo],1):tbCategorias[[#This Row],[Tipo]],"<>Receita")) -> 2 | I10: Investimento | J10: Boleto
B11: Mercado | C11: Despesa | D11: Essencial | E11: 950 | F11: =IF(tbCategorias[[#This Row],[Tipo]]="Receita","",COUNTIF(INDEX(tbCategorias[Tipo],1):tbCategorias[[#This Row],[Tipo]],"<>Receita")) -> 3 | J11: Dinheiro
B12: Transporte | C12: Despesa | D12: Essencial | E12: 380 | F12: =IF(tbCategorias[[#This Row],[Tipo]]="Receita","",COUNTIF(INDEX(tbCategorias[Tipo],1):tbCategorias[[#This Row],[Tipo]],"<>Receita")) -> 4
B13: Saúde | C13: Despesa | D13: Essencial | E13: 350 | F13: =IF(tbCategorias[[#This Row],[Tipo]]="Receita","",COUNTIF(INDEX(tbCategorias[Tipo],1):tbCategorias[[#This Row],[Tipo]],"<>Receita")) -> 5
B14: Educação | C14: Despesa | D14: Essencial | E14: 150 | F14: =IF(tbCategorias[[#This Row],[Tipo]]="Receita","",COUNTIF(INDEX(tbCategorias[Tipo],1):tbCategorias[[#This Row],[Tipo]],"<>Receita")) -> 6
B15: Restaurantes e delivery | C15: Despesa | D15: Estilo de vida | E15: 350 | F15: =IF(tbCategorias[[#This Row],[Tipo]]="Receita","",COUNTIF(INDEX(tbCategorias[Tipo],1):tbCategorias[[#This Row],[Tipo]],"<>Receita")) -> 7
B16: Lazer | C16: Despesa | D16: Estilo de vida | E16: 250 | F16: =IF(tbCategorias[[#This Row],[Tipo]]="Receita","",COUNTIF(INDEX(tbCategorias[Tipo],1):tbCategorias[[#This Row],[Tipo]],"<>Receita")) -> 8
B17: Assinaturas | C17: Despesa | D17: Estilo de vida | E17: 90 | F17: =IF(tbCategorias[[#This Row],[Tipo]]="Receita","",COUNTIF(INDEX(tbCategorias[Tipo],1):tbCategorias[[#This Row],[Tipo]],"<>Receita")) -> 9
B18: Compras | C18: Despesa | D18: Estilo de vida | E18: 300 | F18: =IF(tbCategorias[[#This Row],[Tipo]]="Receita","",COUNTIF(INDEX(tbCategorias[Tipo],1):tbCategorias[[#This Row],[Tipo]],"<>Receita")) -> 10
B19: Outros | C19: Despesa | D19: Estilo de vida | E19: 100 | F19: =IF(tbCategorias[[#This Row],[Tipo]]="Receita","",COUNTIF(INDEX(tbCategorias[Tipo],1):tbCategorias[[#This Row],[Tipo]],"<>Receita")) -> 11
B20: Investimentos | C20: Investimento | D20: Investimento | E20: 800 | F20: =IF(tbCategorias[[#This Row],[Tipo]]="Receita","",COUNTIF(INDEX(tbCategorias[Tipo],1):tbCategorias[[#This Row],[Tipo]],"<>Receita")) -> 12
B22: Tipo: Receita entra no total recebido; Despesa no total gasto; Investimento conta como dinheiro guardado.
B23: Grupo: usado na divisão 50/30/20 do painel (Essencial, Estilo de vida, Investimento).
B25: Orçamento do mês (despesas) | E25: =SUMIFS(tbCategorias[Orçamento mensal],tbCategorias[Tipo],"Despesa") -> 4540
B26: Investimento planejado no mês | E26: =SUMIFS(tbCategorias[Orçamento mensal],tbCategorias[Tipo],"Investimento") -> 800
B27: Total planejado por mês | E27: =E25+E26 -> 5340

Sheet Metas
B1: Metas
B2: Objetivos de economia. Atualize "Já guardado" quando fizer um aporte.
B3: =HYPERLINK("#'Painel'!A1","Painel") -> Painel | C3: =HYPERLINK("#'Celular'!A1","Celular") -> Celular | D3: =HYPERLINK("#'Lançamentos'!A1","Lançamentos") -> Lançamentos | E3: =HYPERLINK("#'Contas fixas'!A1","Contas") -> Contas | F3: =HYPERLINK("#'Cartão'!A1","Cartão") -> Cartão | G3: =HYPERLINK("#'Dívidas'!A1","Dívidas") -> Dívidas | H3: =HYPERLINK("#'Categorias'!A1","Categorias") -> Categorias | I3: Metas | J3: =HYPERLINK("#'Patrimônio'!A1","Patrimônio") -> Patrimônio | K3: =HYPERLINK("#'Simulador'!A1","Simulador") -> Simulador | L3: =HYPERLINK("#'Resumo'!A1","Resumo") -> Resumo | M3: =HYPERLINK("#'Como usar'!A1","Ajuda") -> Ajuda
B5: Meta | C5: Valor alvo | D5: Já guardado | E5: Prazo | F5: Progresso | G5: Falta | H5: Meses restantes | I5: Guardar por mês
B6: Reserva de emergência | C6: 18000 | D6: 7200 | E6: 46568 | F6: =IF(N(tbMetas[[#This Row],[Valor alvo]])=0,"",tbMetas[[#This Row],[Já guardado]]/tbMetas[[#This Row],[Valor alvo]]) -> 0.4 | G6: =MAX(0,tbMetas[[#This Row],[Valor alvo]]-tbMetas[[#This Row],[Já guardado]]) -> 10800 | H6: =IF(tbMetas[[#This Row],[Prazo]]="","",MAX(1,(YEAR(tbMetas[[#This Row],[Prazo]])-YEAR(TODAY()))*12+MONTH(tbMetas[[#This Row],[Prazo]])-MONTH(TODAY()))) -> 8 | I6: =IF(tbMetas[[#This Row],[Meses restantes]]="","",tbMetas[[#This Row],[Falta]]/tbMetas[[#This Row],[Meses restantes]]) -> 1350
B7: Viagem de férias | C7: 5000 | D7: 1800 | E7: 46418 | F7: =IF(N(tbMetas[[#This Row],[Valor alvo]])=0,"",tbMetas[[#This Row],[Já guardado]]/tbMetas[[#This Row],[Valor alvo]]) -> 0.36 | G7: =MAX(0,tbMetas[[#This Row],[Valor alvo]]-tbMetas[[#This Row],[Já guardado]]) -> 3200 | H7: =IF(tbMetas[[#This Row],[Prazo]]="","",MAX(1,(YEAR(tbMetas[[#This Row],[Prazo]])-YEAR(TODAY()))*12+MONTH(tbMetas[[#This Row],[Prazo]])-MONTH(TODAY()))) -> 3 | I7: =IF(tbMetas[[#This Row],[Meses restantes]]="","",tbMetas[[#This Row],[Falta]]/tbMetas[[#This Row],[Meses restantes]]) -> 1066.6667
B8: Notebook novo | C8: 4500 | D8: 1200 | E8: 46387 | F8: =IF(N(tbMetas[[#This Row],[Valor alvo]])=0,"",tbMetas[[#This Row],[Já guardado]]/tbMetas[[#This Row],[Valor alvo]]) -> 0.26666667 | G8: =MAX(0,tbMetas[[#This Row],[Valor alvo]]-tbMetas[[#This Row],[Já guardado]]) -> 3300 | H8: =IF(tbMetas[[#This Row],[Prazo]]="","",MAX(1,(YEAR(tbMetas[[#This Row],[Prazo]])-YEAR(TODAY()))*12+MONTH(tbMetas[[#This Row],[Prazo]])-MONTH(TODAY()))) -> 2 | I8: =IF(tbMetas[[#This Row],[Meses restantes]]="","",tbMetas[[#This Row],[Falta]]/tbMetas[[#This Row],[Meses restantes]]) -> 1650
B9: Entrada do apartamento | C9: 40000 | D9: 3000 | E9: 47483 | F9: =IF(N(tbMetas[[#This Row],[Valor alvo]])=0,"",tbMetas[[#This Row],[Já guardado]]/tbMetas[[#This Row],[Valor alvo]]) -> 0.075 | G9: =MAX(0,tbMetas[[#This Row],[Valor alvo]]-tbMetas[[#This Row],[Já guardado]]) -> 37000 | H9: =IF(tbMetas[[#This Row],[Prazo]]="","",MAX(1,(YEAR(tbMetas[[#This Row],[Prazo]])-YEAR(TODAY()))*12+MONTH(tbMetas[[#This Row],[Prazo]])-MONTH(TODAY()))) -> 38 | I9: =IF(tbMetas[[#This Row],[Meses restantes]]="","",tbMetas[[#This Row],[Falta]]/tbMetas[[#This Row],[Meses restantes]]) -> 973.68421
B11: Metas e valores são exemplos: troque pelos seus. O painel mostra as 5 primeiras metas.

Sheet Patrimônio
B1: Patrimônio
B2: Onde está o seu dinheiro hoje. Atualize o "Valor atual" de vez em quando, por exemplo no fim de cada mês.
B3: =HYPERLINK("#'Painel'!A1","Painel") -> Painel | C3: =HYPERLINK("#'Celular'!A1","Celular") -> Celular | D3: =HYPERLINK("#'Lançamentos'!A1","Lançamentos") -> Lançamentos | E3: =HYPERLINK("#'Contas fixas'!A1","Contas") -> Contas | F3: =HYPERLINK("#'Cartão'!A1","Cartão") -> Cartão | G3: =HYPERLINK("#'Dívidas'!A1","Dívidas") -> Dívidas | H3: =HYPERLINK("#'Categorias'!A1","Categorias") -> Categorias | I3: =HYPERLINK("#'Metas'!A1","Metas") -> Metas | J3: Patrimônio | K3: =HYPERLINK("#'Simulador'!A1","Simulador") -> Simulador | L3: =HYPERLINK("#'Resumo'!A1","Resumo") -> Resumo | M3: =HYPERLINK("#'Como usar'!A1","Ajuda") -> Ajuda
B5: Item | C5: Tipo | D5: Instituição | E5: Valor aplicado | F5: Valor atual | G5: Rendimento | H5: Rendimento % | I5: % do total | P5: Tipos de patrimônio
B6: Conta corrente | C6: Conta corrente | D6: Nubank | E6: 2350 | F6: 2350 | G6: =tbPatrimonio[[#This Row],[Valor atual]]-tbPatrimonio[[#This Row],[Valor aplicado]] -> 0 | H6: =IF(N(tbPatrimonio[[#This Row],[Valor aplicado]])=0,"",tbPatrimonio[[#This Row],[Rendimento]]/tbPatrimonio[[#This Row],[Valor aplicado]]) -> 0 | I6: =IF(SUM(tbPatrimonio[Valor atual])=0,"",tbPatrimonio[[#This Row],[Valor atual]]/SUM(tbPatrimonio[Valor atual])) -> 0.13538504 | P6: Conta corrente
B7: Reserva de emergência (Tesouro Selic) | C7: Reserva de emergência | D7: Tesouro Direto | E7: 6900 | F7: 7200 | G7: =tbPatrimonio[[#This Row],[Valor atual]]-tbPatrimonio[[#This Row],[Valor aplicado]] -> 300 | H7: =IF(N(tbPatrimonio[[#This Row],[Valor aplicado]])=0,"",tbPatrimonio[[#This Row],[Rendimento]]/tbPatrimonio[[#This Row],[Valor aplicado]]) -> 0.043478261 | I7: =IF(SUM(tbPatrimonio[Valor atual])=0,"",tbPatrimonio[[#This Row],[Valor atual]]/SUM(tbPatrimonio[Valor atual])) -> 0.41479672 | P7: Reserva de emergência
B8: CDB 110% do CDI | C8: Renda fixa | D8: Banco Inter | E8: 3000 | F8: 3185.4 | G8: =tbPatrimonio[[#This Row],[Valor atual]]-tbPatrimonio[[#This Row],[Valor aplicado]] -> 185.4 | H8: =IF(N(tbPatrimonio[[#This Row],[Valor aplicado]])=0,"",tbPatrimonio[[#This Row],[Rendimento]]/tbPatrimonio[[#This Row],[Valor aplicado]]) -> 0.0618 | I8: =IF(SUM(tbPatrimonio[Valor atual])=0,"",tbPatrimonio[[#This Row],[Valor atual]]/SUM(tbPatrimonio[Valor atual])) -> 0.18351298 | P8: Renda fixa
B9: ETF de ações | C9: Renda variável | D9: XP | E9: 1500 | F9: 1622.5 | G9: =tbPatrimonio[[#This Row],[Valor atual]]-tbPatrimonio[[#This Row],[Valor aplicado]] -> 122.5 | H9: =IF(N(tbPatrimonio[[#This Row],[Valor aplicado]])=0,"",tbPatrimonio[[#This Row],[Rendimento]]/tbPatrimonio[[#This Row],[Valor aplicado]]) -> 0.081666667 | I9: =IF(SUM(tbPatrimonio[Valor atual])=0,"",tbPatrimonio[[#This Row],[Valor atual]]/SUM(tbPatrimonio[Valor atual])) -> 0.093473289 | P9: Renda variável
B10: Caixinha da viagem | C10: Renda fixa | D10: Nubank | E10: 1700 | F10: 1800 | G10: =tbPatrimonio[[#This Row],[Valor atual]]-tbPatrimonio[[#This Row],[Valor aplicado]] -> 100 | H10: =IF(N(tbPatrimonio[[#This Row],[Valor aplicado]])=0,"",tbPatrimonio[[#This Row],[Rendimento]]/tbPatrimonio[[#This Row],[Valor aplicado]]) -> 0.058823529 | I10: =IF(SUM(tbPatrimonio[Valor atual])=0,"",tbPatrimonio[[#This Row],[Valor atual]]/SUM(tbPatrimonio[Valor atual])) -> 0.10369918 | P10: Bens
B11: Caixinha do notebook | C11: Renda fixa | D11: Nubank | E11: 1150 | F11: 1200 | G11: =tbPatrimonio[[#This Row],[Valor atual]]-tbPatrimonio[[#This Row],[Valor aplicado]] -> 50 | H11: =IF(N(tbPatrimonio[[#This Row],[Valor aplicado]])=0,"",tbPatrimonio[[#This Row],[Rendimento]]/tbPatrimonio[[#This Row],[Valor aplicado]]) -> 0.043478261 | I11: =IF(SUM(tbPatrimonio[Valor atual])=0,"",tbPatrimonio[[#This Row],[Valor atual]]/SUM(tbPatrimonio[Valor atual])) -> 0.069132787
B14: Resumo | E14: Por tipo | F14: Valor atual | G14: %
B15: Patrimônio total | C15: =SUM(tbPatrimonio[Valor atual]) -> 17357.9 | E15: =P6 -> Conta corrente | F15: =SUMIFS(tbPatrimonio[Valor atual],tbPatrimonio[Tipo],E15) -> 2350 | G15: =IF($C$15=0,"",F15/$C$15) -> 0.13538504
B16: Total aplicado | C16: =SUM(tbPatrimonio[Valor aplicado]) -> 16600 | E16: =P7 -> Reserva de emergência | F16: =SUMIFS(tbPatrimonio[Valor atual],tbPatrimonio[Tipo],E16) -> 7200 | G16: =IF($C$15=0,"",F16/$C$15) -> 0.41479672
B17: Rendimento | C17: =C15-C16 -> 757.9 | E17: =P8 -> Renda fixa | F17: =SUMIFS(tbPatrimonio[Valor atual],tbPatrimonio[Tipo],E17) -> 6185.4 | G17: =IF($C$15=0,"",F17/$C$15) -> 0.35634495
B18: Rendimento % | C18: =IF(C16=0,"",C17/C16) -> 0.045656627 | E18: =P9 -> Renda variável | F18: =SUMIFS(tbPatrimonio[Valor atual],tbPatrimonio[Tipo],E18) -> 1622.5 | G18: =IF($C$15=0,"",F18/$C$15) -> 0.093473289
B19: Dívidas (saldo devedor) | C19: =SUM(tbDividas[Saldo devedor]) -> 12045.201 | E19: =P10 -> Bens | F19: =SUMIFS(tbPatrimonio[Valor atual],tbPatrimonio[Tipo],E19) -> 0 | G19: =IF($C$15=0,"",F19/$C$15) -> 0
B20: Patrimônio líquido | C20: =C15-C19 -> 5312.6995

Sheet Simulador
B1: Simulador de metas
B2: Faça as contas antes de decidir. Mude as células douradas: o resto se recalcula.
B3: =HYPERLINK("#'Painel'!A1","Painel") -> Painel | C3: =HYPERLINK("#'Celular'!A1","Celular") -> Celular | D3: =HYPERLINK("#'Lançamentos'!A1","Lançamentos") -> Lançamentos | E3: =HYPERLINK("#'Contas fixas'!A1","Contas") -> Contas | F3: =HYPERLINK("#'Cartão'!A1","Cartão") -> Cartão | G3: =HYPERLINK("#'Dívidas'!A1","Dívidas") -> Dívidas | H3: =HYPERLINK("#'Categorias'!A1","Categorias") -> Categorias | I3: =HYPERLINK("#'Metas'!A1","Metas") -> Metas | J3: =HYPERLINK("#'Patrimônio'!A1","Patrimônio") -> Patrimônio | K3: Simulador | L3: =HYPERLINK("#'Resumo'!A1","Resumo") -> Resumo | M3: =HYPERLINK("#'Como usar'!A1","Ajuda") -> Ajuda
B5: Quanto preciso guardar por mês? | E5: Em quanto tempo eu chego lá? | P5: Mês | Q5: Saldo | R5: Objetivo
B6: Quero juntar | C6: 20000 | E6: Quero juntar | F6: 50000 | P6: =IF(ISNUMBER($F$11),MAX($F$11,1)*0/24,0*5) -> 0 | Q6: =ROUND(FV($F$10,P6,-$F$8,-$F$7),2) -> 7200 | R6: =$F$6 -> 50000
B7: Já tenho | C7: 5000 | E7: Já tenho | F7: 7200 | P7: =IF(ISNUMBER($F$11),MAX($F$11,1)*1/24,1*5) -> 0.79166667 | Q7: =ROUND(FV($F$10,P7,-$F$8,-$F$7),2) -> 8922.36 | R7: =$F$6 -> 50000
B8: Em quantos meses | C8: 24 | E8: Guardo por mês | F8: =ROUND(MAX(0,(Painel!$B$75-Painel!$E$75)/MONTH(Painel!$M$3)),0) -> 2120 | P8: =IF(ISNUMBER($F$11),MAX($F$11,1)*2/24,2*5) -> 1.5833333 | Q8: =ROUND(FV($F$10,P8,-$F$8,-$F$7),2) -> 10655.58 | R8: =$F$6 -> 50000
B9: Rendimento ao ano | C9: 0.1 | E9: Rendimento ao ano | F9: 0.1 | P9: =IF(ISNUMBER($F$11),MAX($F$11,1)*3/24,3*5) -> 2.375 | Q9: =ROUND(FV($F$10,P9,-$F$8,-$F$7),2) -> 12399.74 | R9: =$F$6 -> 50000
B10: Rendimento ao mês | C10: =(1+C9)^(1/12)-1 -> 0.0079741404 | E10: Rendimento ao mês | F10: =(1+F9)^(1/12)-1 -> 0.0079741404 | P10: =IF(ISNUMBER($F$11),MAX($F$11,1)*4/24,4*5) -> 3.1666667 | Q10: =ROUND(FV($F$10,P10,-$F$8,-$F$7),2) -> 14154.89 | R10: =$F$6 -> 50000
B11: Guardar por mês | C11: =IF(C8<=0,"",IF(C10=0,MAX(0,(C6-C7)/C8),MAX(0,-PMT(C10,C8,-C7,C6)))) -> 529.71076 | E11: Meses até chegar | F11: =IF(F6<=F7,0,IF(F8<=0,"não chega",IFERROR(ROUNDUP(IF(F10=0,(F6-F7)/F8,NPER(F10,-F8,-F7,F6)),0),"não chega"))) -> 19 | P11: =IF(ISNUMBER($F$11),MAX($F$11,1)*5/24,5*5) -> 3.9583333 | Q11: =ROUND(FV($F$10,P11,-$F$8,-$F$7),2) -> 15921.12 | R11: =$F$6 -> 50000
B12: Total que você vai depositar | C12: =IF(C11="","",C11*C8) -> 12713.058 | E12: Em anos | F12: =IF(ISNUMBER(F11),F11/12,"") -> 1.5833333 | P12: =IF(ISNUMBER($F$11),MAX($F$11,1)*6/24,6*5) -> 4.75 | Q12: =ROUND(FV($F$10,P12,-$F$8,-$F$7),2) -> 17698.49 | R12: =$F$6 -> 50000
B13: Ganho com o rendimento | C13: =IF(C11="","",MAX(0,C6-C7-C12)) -> 2286.9418 | E13: Data prevista | F13: =IF(ISNUMBER(F11),EDATE(TODAY(),F11),"") -> 46899 | P13: =IF(ISNUMBER($F$11),MAX($F$11,1)*7/24,7*5) -> 5.5416667 | Q13: =ROUND(FV($F$10,P13,-$F$8,-$F$7),2) -> 19487.07 | R13: =$F$6 -> 50000
P14: =IF(ISNUMBER($F$11),MAX($F$11,1)*8/24,8*5) -> 6.3333333 | Q14: =ROUND(FV($F$10,P14,-$F$8,-$F$7),2) -> 21286.93 | R14: =$F$6 -> 50000
P15: =IF(ISNUMBER($F$11),MAX($F$11,1)*9/24,9*5) -> 7.125 | Q15: =ROUND(FV($F$10,P15,-$F$8,-$F$7),2) -> 23098.14 | R15: =$F$6 -> 50000
B16: Quanto guardar por mês em cada meta | P16: =IF(ISNUMBER($F$11),MAX($F$11,1)*10/24,10*5) -> 7.9166667 | Q16: =ROUND(FV($F$10,P16,-$F$8,-$F$7),2) -> 24920.78 | R16: =$F$6 -> 50000
B17: Meta | C17: Falta | D17: Meses | E17: Sem rendimento | F17: Com rendimento | P17: =IF(ISNUMBER($F$11),MAX($F$11,1)*11/24,11*5) -> 8.7083333 | Q17: =ROUND(FV($F$10,P17,-$F$8,-$F$7),2) -> 26754.92 | R17: =$F$6 -> 50000
B18: =IFERROR(INDEX(tbMetas[Meta],ROWS(B$18:B18)),"") -> Reserva de emergência | C18: =IF($B18="","",INDEX(tbMetas[Falta],ROWS(C$18:C18))) -> 10800 | D18: =IF($B18="","",INDEX(tbMetas[Meses restantes],ROWS(D$18:D18))) -> 8 | E18: =IF($B18="","",INDEX(tbMetas[Guardar por mês],ROWS(E$18:E18))) -> 1350 | F18: =IF(OR($B18="",N(D18)=0),"",MAX(0,-PMT($C$10,D18,-INDEX(tbMetas[Já guardado],ROWS(F$18:F18)),INDEX(tbMetas[Valor alvo],ROWS(F$18:F18))))) -> 1255.3572 | P18: =IF(ISNUMBER($F$11),MAX($F$11,1)*12/24,12*5) -> 9.5 | Q18: =ROUND(FV($F$10,P18,-$F$8,-$F$7),2) -> 28600.62 | R18: =$F$6 -> 50000
B19: =IFERROR(INDEX(tbMetas[Meta],ROWS(B$18:B19)),"") -> Viagem de férias | C19: =IF($B19="","",INDEX(tbMetas[Falta],ROWS(C$18:C19))) -> 3200 | D19: =IF($B19="","",INDEX(tbMetas[Meses restantes],ROWS(D$18:D19))) -> 3 | E19: =IF($B19="","",INDEX(tbMetas[Guardar por mês],ROWS(E$18:E19))) -> 1066.6667 | F19: =IF(OR($B19="",N(D19)=0),"",MAX(0,-PMT($C$10,D19,-INDEX(tbMetas[Já guardado],ROWS(F$18:F19)),INDEX(tbMetas[Valor alvo],ROWS(F$18:F19))))) -> 1043.8525 | P19: =IF(ISNUMBER($F$11),MAX($F$11,1)*13/24,13*5) -> 10.291667 | Q19: =ROUND(FV($F$10,P19,-$F$8,-$F$7),2) -> 30457.97 | R19: =$F$6 -> 50000
B20: =IFERROR(INDEX(tbMetas[Meta],ROWS(B$18:B20)),"") -> Notebook novo | C20: =IF($B20="","",INDEX(tbMetas[Falta],ROWS(C$18:C20))) -> 3300 | D20: =IF($B20="","",INDEX(tbMetas[Meses restantes],ROWS(D$18:D20))) -> 2 | E20: =IF($B20="","",INDEX(tbMetas[Guardar por mês],ROWS(E$18:E20))) -> 1650 | F20: =IF(OR($B20="",N(D20)=0),"",MAX(0,-PMT($C$10,D20,-INDEX(tbMetas[Já guardado],ROWS(F$18:F20)),INDEX(tbMetas[Valor alvo],ROWS(F$18:F20))))) -> 1633.8785 | P20: =IF(ISNUMBER($F$11),MAX($F$11,1)*14/24,14*5) -> 11.083333 | Q20: =ROUND(FV($F$10,P20,-$F$8,-$F$7),2) -> 32327.03 | R20: =$F$6 -> 50000
B21: =IFERROR(INDEX(tbMetas[Meta],ROWS(B$18:B21)),"") -> Entrada do apartamento | C21: =IF($B21="","",INDEX(tbMetas[Falta],ROWS(C$18:C21))) -> 37000 | D21: =IF($B21="","",INDEX(tbMetas[Meses restantes],ROWS(D$18:D21))) -> 38 | E21: =IF($B21="","",INDEX(tbMetas[Guardar por mês],ROWS(E$18:E21))) -> 973.68421 | F21: =IF(OR($B21="",N(D21)=0),"",MAX(0,-PMT($C$10,D21,-INDEX(tbMetas[Já guardado],ROWS(F$18:F21)),INDEX(tbMetas[Valor alvo],ROWS(F$18:F21))))) -> 813.52668 | P21: =IF(ISNUMBER($F$11),MAX($F$11,1)*15/24,15*5) -> 11.875 | Q21: =ROUND(FV($F$10,P21,-$F$8,-$F$7),2) -> 34207.88 | R21: =$F$6 -> 50000
B22: =IFERROR(INDEX(tbMetas[Meta],ROWS(B$18:B22)),"") | C22: =IF($B22="","",INDEX(tbMetas[Falta],ROWS(C$18:C22))) | D22: =IF($B22="","",INDEX(tbMetas[Meses restantes],ROWS(D$18:D22))) | E22: =IF($B22="","",INDEX(tbMetas[Guardar por mês],ROWS(E$18:E22))) | F22: =IF(OR($B22="",N(D22)=0),"",MAX(0,-PMT($C$10,D22,-INDEX(tbMetas[Já guardado],ROWS(F$18:F22)),INDEX(tbMetas[Valor alvo],ROWS(F$18:F22))))) | P22: =IF(ISNUMBER($F$11),MAX($F$11,1)*16/24,16*5) -> 12.666667 | Q22: =ROUND(FV($F$10,P22,-$F$8,-$F$7),2) -> 36100.59 | R22: =$F$6 -> 50000
B23: "Com rendimento" usa a taxa do primeiro simulador (célula C9). A diferença é o quanto os juros trabalham por você. | P23: =IF(ISNUMBER($F$11),MAX($F$11,1)*17/24,17*5) -> 13.458333 | Q23: =ROUND(FV($F$10,P23,-$F$8,-$F$7),2) -> 38005.25 | R23: =$F$6 -> 50000
P24: =IF(ISNUMBER($F$11),MAX($F$11,1)*18/24,18*5) -> 14.25 | Q24: =ROUND(FV($F$10,P24,-$F$8,-$F$7),2) -> 39921.91 | R24: =$F$6 -> 50000
P25: =IF(ISNUMBER($F$11),MAX($F$11,1)*19/24,19*5) -> 15.041667 | Q25: =ROUND(FV($F$10,P25,-$F$8,-$F$7),2) -> 41850.67 | R25: =$F$6 -> 50000
P26: =IF(ISNUMBER($F$11),MAX($F$11,1)*20/24,20*5) -> 15.833333 | Q26: =ROUND(FV($F$10,P26,-$F$8,-$F$7),2) -> 43791.59 | R26: =$F$6 -> 50000
P27: =IF(ISNUMBER($F$11),MAX($F$11,1)*21/24,21*5) -> 16.625 | Q27: =ROUND(FV($F$10,P27,-$F$8,-$F$7),2) -> 45744.76 | R27: =$F$6 -> 50000
P28: =IF(ISNUMBER($F$11),MAX($F$11,1)*22/24,22*5) -> 17.416667 | Q28: =ROUND(FV($F$10,P28,-$F$8,-$F$7),2) -> 47710.24 | R28: =$F$6 -> 50000
P29: =IF(ISNUMBER($F$11),MAX($F$11,1)*23/24,23*5) -> 18.208333 | Q29: =ROUND(FV($F$10,P29,-$F$8,-$F$7),2) -> 49688.12 | R29: =$F$6 -> 50000
P30: =IF(ISNUMBER($F$11),MAX($F$11,1)*24/24,24*5) -> 19 | Q30: =ROUND(FV($F$10,P30,-$F$8,-$F$7),2) -> 51678.48 | R30: =$F$6 -> 50000

Sheet Resumo
B1: Resumo mensal
B2: Doze meses a partir do primeiro mês. Os gráficos do painel usam esta tabela.
B3: =HYPERLINK("#'Painel'!A1","Painel") -> Painel | C3: =HYPERLINK("#'Celular'!A1","Celular") -> Celular | D3: =HYPERLINK("#'Lançamentos'!A1","Lançamentos") -> Lançamentos | E3: =HYPERLINK("#'Contas fixas'!A1","Contas") -> Contas | F3: =HYPERLINK("#'Cartão'!A1","Cartão") -> Cartão | G3: =HYPERLINK("#'Dívidas'!A1","Dívidas") -> Dívidas | H3: =HYPERLINK("#'Categorias'!A1","Categorias") -> Categorias | I3: =HYPERLINK("#'Metas'!A1","Metas") -> Metas | J3: =HYPERLINK("#'Patrimônio'!A1","Patrimônio") -> Patrimônio | K3: =HYPERLINK("#'Simulador'!A1","Simulador") -> Simulador | L3: Resumo | M3: =HYPERLINK("#'Como usar'!A1","Ajuda") -> Ajuda
B4: Primeiro mês | C4: 46023
B6: Mês | C6: Receitas | D6: Despesas | E6: Investido | F6: Saldo do mês | G6: Saldo acumulado | H6: Taxa de poupança
B7: =$C$4 -> 46023 | C7: =SUMIFS(tbLancamentos[Valor],tbLancamentos[Mês],$B7,tbLancamentos[Tipo],"Receita") -> 5883.79 | D7: =SUMIFS(tbLancamentos[Valor],tbLancamentos[Mês],$B7,tbLancamentos[Tipo],"Despesa") -> 3566.01 | E7: =SUMIFS(tbLancamentos[Valor],tbLancamentos[Mês],$B7,tbLancamentos[Tipo],"Investimento") -> 600 | F7: =C7-D7-E7 -> 1717.78 | G7: =SUM($F$7:F7) -> 1717.78 | H7: =IF(C7=0,"",(C7-D7)/C7) -> 0.39392636
B8: =EDATE(B7,1) -> 46054 | C8: =SUMIFS(tbLancamentos[Valor],tbLancamentos[Mês],$B8,tbLancamentos[Tipo],"Receita") -> 6754.84 | D8: =SUMIFS(tbLancamentos[Valor],tbLancamentos[Mês],$B8,tbLancamentos[Tipo],"Despesa") -> 3889.91 | E8: =SUMIFS(tbLancamentos[Valor],tbLancamentos[Mês],$B8,tbLancamentos[Tipo],"Investimento") -> 600 | F8: =C8-D8-E8 -> 2264.93 | G8: =SUM($F$7:F8) -> 3982.71 | H8: =IF(C8=0,"",(C8-D8)/C8) -> 0.42412996
B9: =EDATE(B8,1) -> 46082 | C9: =SUMIFS(tbLancamentos[Valor],tbLancamentos[Mês],$B9,tbLancamentos[Tipo],"Receita") -> 6668.83 | D9: =SUMIFS(tbLancamentos[Valor],tbLancamentos[Mês],$B9,tbLancamentos[Tipo],"Despesa") -> 4109.46 | E9: =SUMIFS(tbLancamentos[Valor],tbLancamentos[Mês],$B9,tbLancamentos[Tipo],"Investimento") -> 600 | F9: =C9-D9-E9 -> 1959.37 | G9: =SUM($F$7:F9) -> 5942.08 | H9: =IF(C9=0,"",(C9-D9)/C9) -> 0.38378096
B10: =EDATE(B9,1) -> 46113 | C10: =SUMIFS(tbLancamentos[Valor],tbLancamentos[Mês],$B10,tbLancamentos[Tipo],"Receita") -> 5800 | D10: =SUMIFS(tbLancamentos[Valor],tbLancamentos[Mês],$B10,tbLancamentos[Tipo],"Despesa") -> 3936.94 | E10: =SUMIFS(tbLancamentos[Valor],tbLancamentos[Mês],$B10,tbLancamentos[Tipo],"Investimento") -> 600 | F10: =C10-D10-E10 -> 1263.06 | G10: =SUM($F$7:F10) -> 7205.14 | H10: =IF(C10=0,"",(C10-D10)/C10) -> 0.32121724
B11: =EDATE(B10,1) -> 46143 | C11: =SUMIFS(tbLancamentos[Valor],tbLancamentos[Mês],$B11,tbLancamentos[Tipo],"Receita") -> 5800 | D11: =SUMIFS(tbLancamentos[Valor],tbLancamentos[Mês],$B11,tbLancamentos[Tipo],"Despesa") -> 3989.11 | E11: =SUMIFS(tbLancamentos[Valor],tbLancamentos[Mês],$B11,tbLancamentos[Tipo],"Investimento") -> 926.39 | F11: =C11-D11-E11 -> 884.5 | G11: =SUM($F$7:F11) -> 8089.64 | H11: =IF(C11=0,"",(C11-D11)/C11) -> 0.31222241
B12: =EDATE(B11,1) -> 46174 | C12: =SUMIFS(tbLancamentos[Valor],tbLancamentos[Mês],$B12,tbLancamentos[Tipo],"Receita") -> 6909.83 | D12: =SUMIFS(tbLancamentos[Valor],tbLancamentos[Mês],$B12,tbLancamentos[Tipo],"Despesa") -> 4300.04 | E12: =SUMIFS(tbLancamentos[Valor],tbLancamentos[Mês],$B12,tbLancamentos[Tipo],"Investimento") -> 600 | F12: =C12-D12-E12 -> 2009.79 | G12: =SUM($F$7:F12) -> 10099.43 | H12: =IF(C12=0,"",(C12-D12)/C12) -> 0.37769236
B13: =EDATE(B12,1) -> 46204 | C13: =SUMIFS(tbLancamentos[Valor],tbLancamentos[Mês],$B13,tbLancamentos[Tipo],"Receita") -> 5800 | D13: =SUMIFS(tbLancamentos[Valor],tbLancamentos[Mês],$B13,tbLancamentos[Tipo],"Despesa") -> 4258.87 | E13: =SUMIFS(tbLancamentos[Valor],tbLancamentos[Mês],$B13,tbLancamentos[Tipo],"Investimento") -> 859.76 | F13: =C13-D13-E13 -> 681.37 | G13: =SUM($F$7:F13) -> 10780.8 | H13: =IF(C13=0,"",(C13-D13)/C13) -> 0.26571207
B14: =EDATE(B13,1) -> 46235 | C14: =SUMIFS(tbLancamentos[Valor],tbLancamentos[Mês],$B14,tbLancamentos[Tipo],"Receita") -> 5939.4 | D14: =SUMIFS(tbLancamentos[Valor],tbLancamentos[Mês],$B14,tbLancamentos[Tipo],"Despesa") -> 4070.43 | E14: =SUMIFS(tbLancamentos[Valor],tbLancamentos[Mês],$B14,tbLancamentos[Tipo],"Investimento") -> 600 | F14: =C14-D14-E14 -> 1268.97 | G14: =SUM($F$7:F14) -> 12049.77 | H14: =IF(C14=0,"",(C14-D14)/C14) -> 0.3146732
B15: =EDATE(B14,1) -> 46266 | C15: =SUMIFS(tbLancamentos[Valor],tbLancamentos[Mês],$B15,tbLancamentos[Tipo],"Receita") -> 5800 | D15: =SUMIFS(tbLancamentos[Valor],tbLancamentos[Mês],$B15,tbLancamentos[Tipo],"Despesa") -> 3742.25 | E15: =SUMIFS(tbLancamentos[Valor],tbLancamentos[Mês],$B15,tbLancamentos[Tipo],"Investimento") -> 1017.04 | F15: =C15-D15-E15 -> 1040.71 | G15: =SUM($F$7:F15) -> 13090.48 | H15: =IF(C15=0,"",(C15-D15)/C15) -> 0.35478448
B16: =EDATE(B15,1) -> 46296 | C16: =SUMIFS(tbLancamentos[Valor],tbLancamentos[Mês],$B16,tbLancamentos[Tipo],"Receita") -> 5800 | D16: =SUMIFS(tbLancamentos[Valor],tbLancamentos[Mês],$B16,tbLancamentos[Tipo],"Despesa") -> 4095 | E16: =SUMIFS(tbLancamentos[Valor],tbLancamentos[Mês],$B16,tbLancamentos[Tipo],"Investimento") -> 851.49 | F16: =C16-D16-E16 -> 853.51 | G16: =SUM($F$7:F16) -> 13943.99 | H16: =IF(C16=0,"",(C16-D16)/C16) -> 0.29396552
B17: =EDATE(B16,1) -> 46327 | C17: =SUMIFS(tbLancamentos[Valor],tbLancamentos[Mês],$B17,tbLancamentos[Tipo],"Receita") -> 0 | D17: =SUMIFS(tbLancamentos[Valor],tbLancamentos[Mês],$B17,tbLancamentos[Tipo],"Despesa") -> 0 | E17: =SUMIFS(tbLancamentos[Valor],tbLancamentos[Mês],$B17,tbLancamentos[Tipo],"Investimento") -> 0 | F17: =C17-D17-E17 -> 0 | G17: =SUM($F$7:F17) -> 13943.99 | H17: =IF(C17=0,"",(C17-D17)/C17)
B18: =EDATE(B17,1) -> 46357 | C18: =SUMIFS(tbLancamentos[Valor],tbLancamentos[Mês],$B18,tbLancamentos[Tipo],"Receita") -> 0 | D18: =SUMIFS(tbLancamentos[Valor],tbLancamentos[Mês],$B18,tbLancamentos[Tipo],"Despesa") -> 0 | E18: =SUMIFS(tbLancamentos[Valor],tbLancamentos[Mês],$B18,tbLancamentos[Tipo],"Investimento") -> 0 | F18: =C18-D18-E18 -> 0 | G18: =SUM($F$7:F18) -> 13943.99 | H18: =IF(C18=0,"",(C18-D18)/C18)
B19: Total | C19: =SUM(C7:C18) -> 61156.69 | D19: =SUM(D7:D18) -> 39958.02 | E19: =SUM(E7:E18) -> 7254.68 | F19: =SUM(F7:F18) -> 13943.99 | H19: =IF(C19=0,"",(C19-D19)/C19) -> 0.3466288

Sheet Como usar
B1: Como usar
B3: =HYPERLINK("#'Painel'!A1","Painel") -> Painel | C3: =HYPERLINK("#'Celular'!A1","Celular") -> Celular | D3: =HYPERLINK("#'Lançamentos'!A1","Lançamentos") -> Lançamentos | E3: =HYPERLINK("#'Contas fixas'!A1","Contas") -> Contas | F3: =HYPERLINK("#'Cartão'!A1","Cartão") -> Cartão | G3: =HYPERLINK("#'Dívidas'!A1","Dívidas") -> Dívidas | H3: =HYPERLINK("#'Categorias'!A1","Categorias") -> Categorias | I3: =HYPERLINK("#'Metas'!A1","Metas") -> Metas | J3: =HYPERLINK("#'Patrimônio'!A1","Patrimônio") -> Patrimônio | K3: =HYPERLINK("#'Simulador'!A1","Simulador") -> Simulador | L3: =HYPERLINK("#'Resumo'!A1","Resumo") -> Resumo | M3: Ajuda
B5: Passo a passo
B6: 1. Lançamentos: anote cada entrada e saída (data, descrição, categoria, valor e forma de pagamento). Escreva logo abaixo da última linha que a tabela cresce sozinha.
B7: O valor é sempre positivo. Tipo, Grupo e Mês são preenchidos sozinhos (colunas cinza).
B8: 2. Categorias: ajuste os nomes, o tipo (Receita, Despesa ou Investimento), o grupo e o orçamento mensal. Categorias novas aparecem nas listas e no painel.
B9: 3. Contas fixas: cadastre as contas do mês com o dia do vencimento. Quando lançar o pagamento com a mesma descrição, ela aparece como paga.
B10: 4. Metas: cadastre seus objetivos e atualize "Já guardado". A planilha calcula quanto falta e quanto guardar por mês até o prazo.
B11: 5. Patrimônio: liste contas, reserva e investimentos com o valor aplicado e o valor atual. Com as dívidas, a aba mostra o patrimônio líquido.
B12: Cartão: cadastre seus cartões e as compras parceladas. A cada mês, lance a parcela em Lançamentos com a mesma descrição da compra.
B13: Dívidas: financiamentos e empréstimos. Atualize "Parcelas pagas" todo mês; o saldo devedor e os juros restantes se recalculam.
B14: Simulador: quanto guardar por mês para chegar a um valor, em quanto tempo você chega lá e quanto guardar para cada meta.
B15: 6. Painel: escolha o mês no topo. Indicadores, orçamento, divisão 50/30/20, metas, gráficos e o mapa de calor se atualizam.
B16: 7. Celular: versão em uma coluna para a tela do celular, com seletor de mês próprio. Abra pelo app Excel com a planilha no OneDrive.
... B33: Pode usar à vontade para organizar as suas finanças. Se compartilhar, mantenha os créditos.
B34: =HYPERLINK("https://ottavvi.github.io/site-portfolio/","Criado por Otávio · ottavvi.dev") -> Criado por Otávio · ottavvi.dev

Sheet Calc
B1: Cálculos auxiliares dos gráficos do painel. Não precisa editar.
G2: Valor | H2: Ocorrência | I2: Linha | K2: Categoria | L2: Gasto (celular) | M2: Top | N2: Nome
B3: Essencial | C3: =SUMIFS(tbLancamentos[Valor],tbLancamentos[Mês],Painel!$M$3,tbLancamentos[Grupo],B3) -> 3107.4 | E3: =Painel!$B$7 -> 5800 | G3: =IFERROR(_xlfn.AGGREGATE(14,6,tbLancamentos[Valor]/((tbLancamentos[Mês]=Painel!$M$3)*(tbLancamentos[Tipo]="Despesa")),ROWS(G$3:G3)),"") -> 1200 | H3: =IF(G3="","",COUNTIF(G$3:G3,G3)) -> 1 | I3: =IF(G3="","",_xlfn.AGGREGATE(15,6,(ROW(tbLancamentos[Valor])-ROW(tbLancamentos[[#Headers],[Valor]]))/((tbLancamentos[Mês]=Painel!$M$3)*(tbLancamentos[Tipo]="Despesa")*(tbLancamentos[Valor]=G3)),H3)) -> 274 | K3: =Painel!B29 -> Moradia | L3: =IF(K3="","",IF(INDEX(tbCategorias[Tipo],MATCH(K3,tbCategorias[Categoria],0))<>"Despesa","",SUMIFS(tbLancamentos[Valor],tbLancamentos[Mês],Celular!$C$6,tbLancamentos[Categoria],K3)+ROWS(L$3:L3)/1000000)) -> 1200 | M3: =IFERROR(LARGE($L$3:$L$17,ROWS(M$3:M3)),"") -> 1200 | N3: =IF(M3="","",INDEX($K$3:$K$17,MATCH(M3,$L$3:$L$17,0))) -> Moradia
B4: Estilo de vida | C4: =SUMIFS(tbLancamentos[Valor],tbLancamentos[Mês],Painel!$M$3,tbLancamentos[Grupo],B4) -> 987.6 | G4: =IFERROR(_xlfn.AGGREGATE(14,6,tbLancamentos[Valor]/((tbLancamentos[Mês]=Painel!$M$3)*(tbLancamentos[Tipo]="Despesa")),ROWS(G$3:G4)),"") -> 406.92 | H4: =IF(G4="","",COUNTIF(G$3:G4,G4)) -> 1 | I4: =IF(G4="","",_xlfn.AGGREGATE(15,6,(ROW(tbLancamentos[Valor])-ROW(tbLancamentos[[#Headers],[Valor]]))/((tbLancamentos[Mês]=Painel!$M$3)*(tbLancamentos[Tipo]="Despesa")*(tbLancamentos[Valor]=G4)),H4)) -> 280 | K4: =Painel!B30 -> Contas da casa | L4: =IF(K4="","",IF(INDEX(tbCategorias[Tipo],MATCH(K4,tbCategorias[Categoria],0))<>"Despesa","",SUMIFS(tbLancamentos[Valor],tbLancamentos[Mês],Celular!$C$6,tbLancamentos[Categoria],K4)+ROWS(L$3:L4)/1000000)) -> 395.05 | M4: =IFERROR(LARGE($L$3:$L$17,ROWS(M$3:M4)),"") -> 908.6 | N4: =IF(M4="","",INDEX($K$3:$K$17,MATCH(M4,$L$3:$L$17,0))) -> Mercado
B5: Investimento | C5: =SUMIFS(tbLancamentos[Valor],tbLancamentos[Mês],Painel!$M$3,tbLancamentos[Grupo],B5) -> 851.49 | G5: =IFERROR(_xlfn.AGGREGATE(14,6,tbLancamentos[Valor]/((tbLancamentos[Mês]=Painel!$M$3)*(tbLancamentos[Tipo]="Despesa")),ROWS(G$3:G5)),"") -> 318.36 | H5: =IF(G5="","",COUNTIF(G$3:G5,G5)) -> 1 | I5: =IF(G5="","",_xlfn.AGGREGATE(15,6,(ROW(tbLancamentos[Valor])-ROW(tbLancamentos[[#Headers],[Valor]]))/((tbLancamentos[Mês]=Painel!$M$3)*(tbLancamentos[Tipo]="Despesa")*(tbLancamentos[Valor]=G5)),H5)) -> 267 | K5: =Painel!B31 -> Mercado | L5: =IF(K5="","",IF(INDEX(tbCategorias[Tipo],MATCH(K5,tbCategorias[Categoria],0))<>"Despesa","",SUMIFS(tbLancamentos[Valor],tbLancamentos[Mês],Celular!$C$6,tbLancamentos[Categoria],K5)+ROWS(L$3:L5)/1000000)) -> 908.6 | M5: =IFERROR(LARGE($L$3:$L$17,ROWS(M$3:M5)),"") -> 406.92001 | N5: =IF(M5="","",INDEX($K$3:$K$17,MATCH(M5,$L$3:$L$17,0))) -> Compras
B6: Sobrou | C6: =MAX(0,Painel!$K$7) -> 853.51 | G6: =IFERROR(_xlfn.AGGREGATE(14,6,tbLancamentos[Valor]/((tbLancamentos[Mês]=Painel!$M$3)*(tbLancamentos[Tipo]="Despesa")),ROWS(G$3:G6)),"") -> 308.9 | H6: =IF(G6="","",COUNTIF(G$3:G6,G6)) -> 1 | I6: =IF(G6="","",_xlfn.AGGREGATE(15,6,(ROW(tbLancamentos[Valor])-ROW(tbLancamentos[[#Headers],[Valor]]))/((tbLancamentos[Mês]=Painel!$M$3)*(tbLancamentos[Tipo]="Despesa")*(tbLancamentos[Valor]=G6)),H6)) -> 278 | K6: =Painel!B32 -> Transporte | L6: =IF(K6="","",IF(INDEX(tbCategorias[Tipo],MATCH(K6,tbCategorias[Categoria],0))<>"Despesa","",SUMIFS(tbLancamentos[Valor],tbLancamentos[Mês],Celular!$C$6,tbLancamentos[Categoria],K6)+ROWS(L$3:L6)/1000000)) -> 314.62 | M6: =IFERROR(LARGE($L$3:$L$17,ROWS(M$3:M6)),"") -> 395.05 | N6: =IF(M6="","",INDEX($K$3:$K$17,MATCH(M6,$L$3:$L$17,0))) -> Contas da casa
G7: =IFERROR(_xlfn.AGGREGATE(14,6,tbLancamentos[Valor]/((tbLancamentos[Mês]=Painel!$M$3)*(tbLancamentos[Tipo]="Despesa")),ROWS(G$3:G7)),"") -> 165.63 | H7: =IF(G7="","",COUNTIF(G$3:G7,G7)) -> 1 | I7: =IF(G7="","",_xlfn.AGGREGATE(15,6,(ROW(tbLancamentos[Valor])-ROW(tbLancamentos[[#Headers],[Valor]]))/((tbLancamentos[Mês]=Painel!$M$3)*(tbLancamentos[Tipo]="Despesa")*(tbLancamentos[Valor]=G7)),H7)) -> 279 | K7: =Painel!B33 -> Saúde | L7: =IF(K7="","",IF(INDEX(tbCategorias[Tipo],MATCH(K7,tbCategorias[Categoria],0))<>"Despesa","",SUMIFS(tbLancamentos[Valor],tbLancamentos[Mês],Celular!$C$6,tbLancamentos[Categoria],K7)+ROWS(L$3:L7)/1000000)) -> 209.23001 | M7: =IFERROR(LARGE($L$3:$L$17,ROWS(M$3:M7)),"") -> 314.62 | N7: =IF(M7="","",INDEX($K$3:$K$17,MATCH(M7,$L$3:$L$17,0))) -> Transporte
G8: =IFERROR(_xlfn.AGGREGATE(14,6,tbLancamentos[Valor]/((tbLancamentos[Mês]=Painel!$M$3)*(tbLancamentos[Tipo]="Despesa")),ROWS(G$3:G8)),"") -> 160.93 | H8: =IF(G8="","",COUNTIF(G$3:G8,G8)) -> 1 | I8: =IF(G8="","",_xlfn.AGGREGATE(15,6,(ROW(tbLancamentos[Valor])-ROW(tbLancamentos[[#Headers],[Valor]]))/((tbLancamentos[Mês]=Painel!$M$3)*(tbLancamentos[Tipo]="Despesa")*(tbLancamentos[Valor]=G8)),H8)) -> 285 | K8: =Painel!B34 -> Educação | L8: =IF(K8="","",IF(INDEX(tbCategorias[Tipo],MATCH(K8,tbCategorias[Categoria],0))<>"Despesa","",SUMIFS(tbLancamentos[Valor],tbLancamentos[Mês],Celular!$C$6,tbLancamentos[Categoria],K8)+ROWS(L$3:L8)/1000000)) -> 79.900006
G9: =IFERROR(_xlfn.AGGREGATE(14,6,tbLancamentos[Valor]/((tbLancamentos[Mês]=Painel!$M$3)*(tbLancamentos[Tipo]="Despesa")),ROWS(G$3:G9)),"") -> 153.36 | H9: =IF(G9="","",COUNTIF(G$3:G9,G9)) -> 1 | I9: =IF(G9="","",_xlfn.AGGREGATE(15,6,(ROW(tbLancamentos[Valor])-ROW(tbLancamentos[[#Headers],[Valor]]))/((tbLancamentos[Mês]=Painel!$M$3)*(tbLancamentos[Tipo]="Despesa")*(tbLancamentos[Valor]=G9)),H9)) -> 289 | K9: =Painel!B35 -> Restaurantes e delivery | L9: =IF(K9="","",IF(INDEX(tbCategorias[Tipo],MATCH(K9,tbCategorias[Categoria],0))<>"Despesa","",SUMIFS(tbLancamentos[Valor],tbLancamentos[Mês],Celular!$C$6,tbLancamentos[Categoria],K9)+ROWS(L$3:L9)/1000000)) -> 206.14001
B10: =Categorias!J7 -> Pix | C10: =SUMIFS(tbLancamentos[Valor],tbLancamentos[Mês],Painel!$M$3,tbLancamentos[Pagamento],B10,tbLancamentos[Tipo],"<>Receita") -> 1290.02 | E10: =SUM(C10:C14) -> 4946.49 | K10: =Painel!B36 -> Lazer | L10: =IF(K10="","",IF(INDEX(tbCategorias[Tipo],MATCH(K10,tbCategorias[Categoria],0))<>"Despesa","",SUMIFS(tbLancamentos[Valor],tbLancamentos[Mês],Celular!$C$6,tbLancamentos[Categoria],K10)+ROWS(L$3:L10)/1000000)) -> 178.11001
B11: =Categorias!J8 -> Cartão de crédito | C11: =SUMIFS(tbLancamentos[Valor],tbLancamentos[Mês],Painel!$M$3,tbLancamentos[Pagamento],B11,tbLancamentos[Tipo],"<>Receita") -> 1738.24 | K11: =Painel!B37 -> Assinaturas | L11: =IF(K11="","",IF(INDEX(tbCategorias[Tipo],MATCH(K11,tbCategorias[Categoria],0))<>"Despesa","",SUMIFS(tbLancamentos[Valor],tbLancamentos[Mês],Celular!$C$6,tbLancamentos[Categoria],K11)+ROWS(L$3:L11)/1000000)) -> 66.800009
B12: =Categorias!J9 -> Débito | C12: =SUMIFS(tbLancamentos[Valor],tbLancamentos[Mês],Painel!$M$3,tbLancamentos[Pagamento],B12,tbLancamentos[Tipo],"<>Receita") -> 310.26 | K12: =Painel!B38 -> Compras | L12: =IF(K12="","",IF(INDEX(tbCategorias[Tipo],MATCH(K12,tbCategorias[Categoria],0))<>"Despesa","",SUMIFS(tbLancamentos[Valor],tbLancamentos[Mês],Celular!$C$6,tbLancamentos[Categoria],K12)+ROWS(L$3:L12)/1000000)) -> 406.92001
B13: =Categorias!J10 -> Boleto | C13: =SUMIFS(tbLancamentos[Valor],tbLancamentos[Mês],Painel!$M$3,tbLancamentos[Pagamento],B13,tbLancamentos[Tipo],"<>Receita") -> 1505.15 | K13: =Painel!B39 -> Outros | L13: =IF(K13="","",IF(INDEX(tbCategorias[Tipo],MATCH(K13,tbCategorias[Categoria],0))<>"Despesa","",SUMIFS(tbLancamentos[Valor],tbLancamentos[Mês],Celular!$C$6,tbLancamentos[Categoria],K13)+ROWS(L$3:L13)/1000000)) -> 129.63001
B14: =Categorias!J11 -> Dinheiro | C14: =SUMIFS(tbLancamentos[Valor],tbLancamentos[Mês],Painel!$M$3,tbLancamentos[Pagamento],B14,tbLancamentos[Tipo],"<>Receita") -> 102.82 | K14: =Painel!B40 -> Investimentos | L14: =IF(K14="","",IF(INDEX(tbCategorias[Tipo],MATCH(K14,tbCategorias[Categoria],0))<>"Despesa","",SUMIFS(tbLancamentos[Valor],tbLancamentos[Mês],Celular!$C$6,tbLancamentos[Categoria],K14)+ROWS(L$3:L14)/1000000))
K15: =Painel!B41 | L15: =IF(K15="","",IF(INDEX(tbCategorias[Tipo],MATCH(K15,tbCategorias[Categoria],0))<>"Despesa","",SUMIFS(tbLancamentos[Valor],tbLancamentos[Mês],Celular!$C$6,tbLancamentos[Categoria],K15)+ROWS(L$3:L15)/1000000))
K16: =Painel!B42 | L16: =IF(K16="","",IF(INDEX(tbCategorias[Tipo],MATCH(K16,tbCategorias[Categoria],0))<>"Despesa","",SUMIFS(tbLancamentos[Valor],tbLancamentos[Mês],Celular!$C$6,tbLancamentos[Categoria],K16)+ROWS(L$3:L16)/1000000))
B17: Guardado | C17: =MAX(0,MIN(1,Painel!$N$7)) -> 0.29396552 | E17: =Painel!$N$7 -> 0.29396552 | K17: =Painel!B43 | L17: =IF(K17="","",IF(INDEX(tbCategorias[Tipo],MATCH(K17,tbCategorias[Categoria],0))<>"Despesa","",SUMIFS(tbLancamentos[Valor],tbLancamentos[Mês],Celular!$C$6,tbLancamentos[Categoria],K17)+ROWS(L$3:L17)/1000000))
B18: Resto | C18: =1-C17 -> 0.70603448
B19: Metade oculta | C19: 1
